<?xml version="1.0" encoding="utf-8"?>
<LOCALISATION xmlns:xsi="http://www.w3.org/2001/XMLSchema-instance" xmlns:xs="http://www.w3.org/2001/XMLSchema" default_language="en-GB" xmlns="http://home.scedev.net/schema/object">
  <PHRASE>
    <LANG ID="REF">kName</LANG>
    <LANG ID="en-GB">Leather Costume Bundle (Female)</LANG>
    <LANG ID="fr-FR">Pack costume en cuir</LANG>
    <LANG ID="de-DE">Lederkostüm-Paket (Damen)</LANG>
    <LANG ID="it-IT">Pacchetto costume di pelle (donna)</LANG>
    <LANG ID="es-ES">Conjunto de cuero (mujer)</LANG>
    <LANG ID="ko-KR">가죽 의상 세트 (여성)</LANG>
    <LANG ID="en-SG">Leather Costume Bundle (Women)</LANG>
    <LANG ID="zh-HK">皮革服裝組（女用）</LANG>
    <LANG ID="zh-TW">皮革服裝組（女用）</LANG>
    <LANG ID="en-US">Leather Costume Bundle (Female)</LANG>
  </PHRASE>
  <PHRASE>
    <LANG ID="REF">kDesc</LANG>
    <LANG ID="en-GB">This leather outfit will definitely attract attention. Available only in faux. Bundle includes a leather jacket, gloves, boots and shorts. [#Legal]</LANG>
    <LANG ID="fr-FR">Vous ne passerez pas inaperçue avec cette tenue en cuir. 100 % faux cuir. Le pack comprend une veste, des mitaines, des bottes et un short. [#Legal]</LANG>
    <LANG ID="de-DE">Dieses Lederoutfit sorgt auf jeden Fall für Aufsehen. Nur aus Kunstleder erhältlich. Das Paket beinhaltet Lederjacke, Handschuhe, Stiefel und Shorts. [#Legal]</LANG>
    <LANG ID="it-IT">Questa tenuta di pelle attirerà sicuramente l'attenzione. Disponibile soltanto in pelle ecologica. Il pacchetto include giacca, guanti, stivali e pantaloncini di pelle. [#Legal]</LANG>
    <LANG ID="es-ES">Este traje de cuero atraerá la atención, sin lugar a dudas. Disponible solo en cuero artificial. El conjunto comprende chaqueta, guantes, botas y pantalón corto. [#Legal]</LANG>
    <LANG ID="ko-KR">이 가죽 의상은 모두의 관심을 끌기에 충분합니다. 이 세트는 재킷, 장갑, 부츠, 그리고 반바지를 포함합니다. [#Legal]</LANG>
    <LANG ID="en-SG">This leather outfit will definitely attract attention. Available only in faux. Bundle includes a leather jacket, gloves, boots and shorts. [#Legal]</LANG>
    <LANG ID="zh-HK">這皮革服裝必定會吸引眾人注意。只有以人造皮革製成的款式。本服裝組包括皮外套、手套、靴及短褲。[#Legal]</LANG>
    <LANG ID="zh-TW">這皮革服裝必定會吸引眾人注意。只有以人造皮革製成的款式。本服裝組包括皮外套、手套、靴及短褲。[#Legal]</LANG>
    <LANG ID="en-US">This leather outfit will definitely attract attention. Available only in faux. Bundle includes a leather jacket, gloves, boots and shorts. [#Legal]</LANG>
  </PHRASE>
</LOCALISATION>