<?xml version="1.0" encoding="utf-8"?>
<LOCALISATION xmlns:xsi="http://www.w3.org/2001/XMLSchema-instance" xmlns:xs="http://www.w3.org/2001/XMLSchema" default_language="en-US" xmlns="http://home.scedev.net/schema/object">
  <PHRASE>
    <LANG ID="REF">kName</LANG>
    <LANG ID="en-GB">Anime Ninja Value Pack (for Female)</LANG>
    <LANG ID="fr-FR">Pack occasion ninja Anime (pour femme)</LANG>
    <LANG ID="de-DE">Anime-Ninja-Vorteilspaket (Damen)</LANG>
    <LANG ID="it-IT">Pacchetto convenienza ninja degli anime (per donna)</LANG>
    <LANG ID="es-ES">Paquete extra de ninja de anime (para mujer)</LANG>
    <LANG ID="ja-JP">Anime Ninja Value Pack (for Female)</LANG>
    <LANG ID="ko-KR">Anime Ninja Value Pack (for Female)</LANG>
    <LANG ID="en-SG">Anime Ninja Value Pack (for Female)</LANG>
    <LANG ID="zh-HK">Anime Ninja Value Pack (for Female)</LANG>
    <LANG ID="zh-TW">Anime Ninja Value Pack (for Female)</LANG>
    <LANG ID="en-US">Anime Ninja Value Pack (for Female)</LANG>
  </PHRASE>
  <PHRASE>
    <LANG ID="REF">kDesc</LANG>
    <LANG ID="en-GB">Anime Ninja Value Pack (for Female)\n\n 
This bundle includes the following items: \n 
• The Norika\n
• Anime Ninja Shinobi Shozoku - Black (for Female)\n
• Anime Ninja Kunai and Gloves - Black (for Female)\n
• Anime Ninja Jika-tabi Boots - Black (for Female)\n
Live your life as a noble Ninja or just cosplay for fun. [#Legal]</LANG>
    <LANG ID="fr-FR">Pack occasion ninja Anime (pour femme)\n\n 
Ce pack inclut les éléments suivants : \n 
• Le Norika\n
• Shinobi Shozoku ninja Anime - Noir (pour femme)\n
• Kunaï et gants ninja Anime - Noirs (pour femme)\n
• Jika-tabi ninja Anime - Noirs (pour femme)\n
Vivez la vie d'un noble ninja ou déguisez-vous pour vous amuser. [#Legal]</LANG>
    <LANG ID="de-DE">Anime-Ninja-Vorteilspaket (Damen)\n\n 
Dieses Paket enthält: \n 
• Norika\n
• Anime-Ninja-Shinobi-Shozoku - Schwarz (Damen)\n
• Anime-Ninja-Kunai und Handschuhe - Schwarz (Damen)\n
• Anime-Ninja-Jika-Tabi-Stiefel - Schwarz (Damen)\n
Lebe als edler Ninja oder hab einfach Spaß am Cosplay. [#Legal]</LANG>
    <LANG ID="it-IT">Pacchetto convenienza ninja degli anime (per donna)\n\n 
Questo pacchetto include quanto segue: \n 
• Norika\n
• Shinobi Shozoku da ninja degli anime - Nero (per donna)\n
• Guanti e kunai da ninja degli anime - Nero (per donna)\n
• Stivali Jika-tabi da ninja degli anime - Nero (per donna)\n
Vivi la tua vita come un nobile ninja oppure travestiti per divertirti. [#Legal]</LANG>
    <LANG ID="es-ES">Paquete extra de ninja de anime (para mujer)\n\n 
Este paquete incluye los siguientes objetos: \n 
• El Norika.\n
• Shinobi Shozoku de ninja de anime; negro (para mujer).\n
• Kunai y guantes de ninja de anime; negros (para mujer).\n
• Botas Jika-tabi de ninja de anime; negras (para mujer).\n
Vive tu vida como un noble ninja o simplemente disfrázate por diversión. [#Legal]</LANG>
    <LANG ID="ja-JP">Anime Ninja Value Pack (for Female)\n\n 
This bundle includes the following items: \n 
• The Norika\n
• Anime Ninja Shinobi Shozoku - Black (for Female)\n
• Anime Ninja Kunai and Gloves - Black (for Female)\n
• Anime Ninja Jika-tabi Boots - Black (for Female)\n
Live your life as a noble Ninja or just cosplay for fun. [#Legal]</LANG>
    <LANG ID="ko-KR">Anime Ninja Value Pack (for Female)\n\n 
This bundle includes the following items: \n 
• The Norika\n
• Anime Ninja Shinobi Shozoku - Black (for Female)\n
• Anime Ninja Kunai and Gloves - Black (for Female)\n
• Anime Ninja Jika-tabi Boots - Black (for Female)\n
Live your life as a noble Ninja or just cosplay for fun. [#Legal]</LANG>
    <LANG ID="en-SG">Anime Ninja Value Pack (for Female)\n\n 
This bundle includes the following items: \n 
• The Norika\n
• Anime Ninja Shinobi Shozoku - Black (for Female)\n
• Anime Ninja Kunai and Gloves - Black (for Female)\n
• Anime Ninja Jika-tabi Boots - Black (for Female)\n
Live your life as a noble Ninja or just cosplay for fun. [#Legal]</LANG>
    <LANG ID="zh-HK">Anime Ninja Value Pack (for Female)\n\n 
This bundle includes the following items: \n 
• The Norika\n
• Anime Ninja Shinobi Shozoku - Black (for Female)\n
• Anime Ninja Kunai and Gloves - Black (for Female)\n
• Anime Ninja Jika-tabi Boots - Black (for Female)\n
Live your life as a noble Ninja or just cosplay for fun. [#Legal]</LANG>
    <LANG ID="zh-TW">Anime Ninja Value Pack (for Female)\n\n 
This bundle includes the following items: \n 
• The Norika\n
• Anime Ninja Shinobi Shozoku - Black (for Female)\n
• Anime Ninja Kunai and Gloves - Black (for Female)\n
• Anime Ninja Jika-tabi Boots - Black (for Female)\n
Live your life as a noble Ninja or just cosplay for fun. [#Legal]</LANG>
    <LANG ID="en-US">Anime Ninja Value Pack (for Female)\n\n 
This bundle includes the following items: \n 
• The Norika\n
• Anime Ninja Shinobi Shozoku - Black (for Female)\n
• Anime Ninja Kunai and Gloves - Black (for Female)\n
• Anime Ninja Jika-tabi Boots - Black (for Female)\n
Live your life as a noble Ninja or just cosplay for fun. [#Legal]</LANG>
  </PHRASE>
</LOCALISATION>