<?xml version="1.0" encoding="utf-8"?>
<LOCALISATION xmlns:xsi="http://www.w3.org/2001/XMLSchema-instance" xmlns:xs="http://www.w3.org/2001/XMLSchema" default_language="en-GB" xmlns="http://home.scedev.net/schema/object">
  <PHRASE>
    <LANG ID="REF">kName</LANG>
    <LANG ID="en-GB">Rhino Calf Companion</LANG>
    <LANG ID="fr-FR">Compagnon Bébé Rhino</LANG>
    <LANG ID="de-DE">Nashornjunges-Gefährte</LANG>
    <LANG ID="it-IT">Cucciolo Di Rinoceronte Da Compagnia</LANG>
    <LANG ID="es-ES">Mascota Cría De Rinoceronte</LANG>
  </PHRASE>
  <PHRASE>
    <LANG ID="REF">kDesc</LANG>
    <LANG ID="en-GB">Help look after this cute little rhino calf. It’s been on a long journey from South Africa. [#Legal]</LANG>
    <LANG ID="fr-FR">Occupez-vous de ce mignon petit bébé rhinocéros. Il a fait un long voyage depuis l'Afrique du Sud. [#Legal]</LANG>
    <LANG ID="de-DE">Dieses niedliche kleine Nashornbaby braucht Hilfe. Es hat eine lange Reise aus Südafrika hinter sich. [#Legal]</LANG>
    <LANG ID="it-IT">Dai una mano ad accudire questo grazioso cucciolo di rinoceronte. Dal Sudafrica è proprio un lungo viaggio. [#Legal]</LANG>
    <LANG ID="es-ES">Ayuda a cuidar a este pequeño rinoceronte. Ha recorrido un largo camino desde Sudáfrica. [#Legal]</LANG>
    <LANG ID="Batch 1">FY13 [#Legal]</LANG>
  </PHRASE>
  <PHRASE>
    <LANG ID="REF">kCompanionName1</LANG>
    <LANG ID="en-GB">Rhino Calf</LANG>
    <LANG ID="fr-FR">Bébé Rhino</LANG>
    <LANG ID="de-DE">Nashornjunges</LANG>
    <LANG ID="it-IT">Cucciolo Di Rinoceronte</LANG>
    <LANG ID="es-ES">Cría De Rinoceronte</LANG>
  </PHRASE>
</LOCALISATION>