<?xml version="1.0" encoding="utf-8"?>
<LOCALISATION xmlns:xsi="http://www.w3.org/2001/XMLSchema-instance" xmlns:xs="http://www.w3.org/2001/XMLSchema" default_language="en-GB" xmlns="http://home.scedev.net/schema/object">
  <PHRASE>
    <LANG ID="REF">kName</LANG>
    <LANG ID="en-GB">F_Hand_2D_A10</LANG>
    <LANG ID="ja-JP">オパールの指輪（女性用）</LANG>
  </PHRASE>
  <PHRASE>
    <LANG ID="REF">kDesc</LANG>
    <LANG ID="ja-JP">10月の誕生石、オパールの指輪です。\n歓喜・安楽・忍耐という意味が込められています。\n\n身に付けるとおしゃべりファームで、下記の効果があります。\n\nオパールの指輪（女性用）\nしんかの力の獲得数が一つ増える効果があります。 [#Legal]</LANG>
  </PHRASE>
</LOCALISATION>