<?xml version="1.0" encoding="utf-8"?>
<LOCALISATION xmlns:xsi="http://www.w3.org/2001/XMLSchema-instance" xmlns:xs="http://www.w3.org/2001/XMLSchema" default_language="en-US" xmlns="http://home.scedev.net/schema/object">
  <PHRASE>
    <LANG ID="REF">kName</LANG>
    <LANG ID="en-GB">Ayuri Mega Bundle</LANG>
    <LANG ID="fr-FR">Méga pack d'Ayuri</LANG>
    <LANG ID="de-DE">Ayuri-Megapaket</LANG>
    <LANG ID="it-IT">Mega pacchetto Ayuri</LANG>
    <LANG ID="es-ES">Megapaquete de Ayuri</LANG>
    <LANG ID="ja-JP">Ayuri Mega Bundle</LANG>
    <LANG ID="ko-KR">Ayuri Mega Bundle</LANG>
    <LANG ID="en-SG">Ayuri Mega Bundle</LANG>
    <LANG ID="zh-HK">Ayuri Mega Bundle</LANG>
    <LANG ID="zh-TW">Ayuri Mega Bundle</LANG>
    <LANG ID="en-US">Ayuri Mega Bundle</LANG>
  </PHRASE>
  <PHRASE>
    <LANG ID="REF">kDesc</LANG>
    <LANG ID="en-GB">Ayuri Mega Bundle\n\n 
This pack includes the following items: \n 
• The Ayuri\n
• Ayuri's Gothic Lolita Dress - Black\n
• Ayuri's School Blouse with Bow - Red\n
• Ayuri's Tartan Skirt - Red\n
• Ayuri's Heeled Knee-High Boots - White\n
Put together an anime cosplay costume, or maybe just an outrageous outfit! Lockwood has all the finishing touches. [#Legal]</LANG>
    <LANG ID="fr-FR">Méga pack d'Ayuri\n\n 
Ce pack inclut les éléments suivants : \n 
• L'Ayuri\n
• Robe lolita gothique d'Ayuri - Noir\n
• Chemisier scolaire d'Ayuri avec son nœud - Rouge\n
• Jupe en tartan d'Ayuri - Rouge\n
• Bottes montantes à talons d'Ayuri - blanc\n
Composez un cosplay d'anime, ou juste une tenue extravagante ! Lockwood vous fournira les touches finales. [#Legal]</LANG>
    <LANG ID="de-DE">Ayuri-Megapaket\n\n
Dieses Paket enthält: \n 
• Ayuri\n
• Ayuris Gothic-Lolitakleid - Schwarz\n
• Ayuris Schulhemd mit Schleife - Rot\n
• Ayuris Karorock - Rot\n
• Ayuris Kniestiefel - Weiß\n
Ob nun für dein eigenes Cosplay-Kostüm oder einfach ein grandioses Outfit! Lockwood hat sämtliche Accessoires, die du brauchst! [#Legal]</LANG>
    <LANG ID="it-IT">Mega pacchetto Ayuri\n\n 
Questo pacchetto include i seguenti oggetti: \n 
• Ayuri\n
• Abito da Gothic Lolita di Ayuri - Nero\n
• Camicetta con fiocco da scuola di Ayuri - Rosso\n
• Gonna scozzese di Ayuri - Rosso\n
• Stivali al ginocchio con tacchi alti di Ayuri - Bianco\n
Crea un costume da cosplay o forse magari solo un look stravagante! Lockwood ci mette il tocco finale. [#Legal]</LANG>
    <LANG ID="es-ES">Megapaquete de Ayuri\n\n 
Este paquete incluye: \n
• El Ayuri.\n
• Vestido de Lolita gótica de Ayuri; negro.\n
• Blusa de colegiala con lazo de Ayuri; roja.\n
• Falda a cuadros de Ayuri; roja.\n
• Botas altas con tacón de Ayuri; blancas.\n
¡Crea un disfraz de cosplay de anime o sencillamente un modelito extravagante! Lockwood tiene todos los últimos detalles. [#Legal]</LANG>
    <LANG ID="ja-JP">Ayuri Mega Bundle\n\n 
This pack includes the following items: \n 
• The Ayuri\n
• Ayuri's Gothic Lolita Dress - Black\n
• Ayuri's School Blouse with Bow - Red\n
• Ayuri's Tartan Skirt - Red\n
• Ayuri's Heeled Knee-High Boots - White\n
Put together an anime cosplay costume, or maybe just an outrageous outfit! Lockwood has all the finishing touches. [#Legal]</LANG>
    <LANG ID="ko-KR">Ayuri Mega Bundle\n\n 
This pack includes the following items: \n 
• The Ayuri\n
• Ayuri's Gothic Lolita Dress - Black\n
• Ayuri's School Blouse with Bow - Red\n
• Ayuri's Tartan Skirt - Red\n
• Ayuri's Heeled Knee-High Boots - White\n
Put together an anime cosplay costume, or maybe just an outrageous outfit! Lockwood has all the finishing touches. [#Legal]</LANG>
    <LANG ID="en-SG">Ayuri Mega Bundle\n\n 
This pack includes the following items: \n 
• The Ayuri\n
• Ayuri's Gothic Lolita Dress - Black\n
• Ayuri's School Blouse with Bow - Red\n
• Ayuri's Tartan Skirt - Red\n
• Ayuri's Heeled Knee-High Boots - White\n
Put together an anime cosplay costume, or maybe just an outrageous outfit! Lockwood has all the finishing touches. [#Legal]</LANG>
    <LANG ID="zh-HK">Ayuri Mega Bundle\n\n 
This pack includes the following items: \n 
• The Ayuri\n
• Ayuri's Gothic Lolita Dress - Black\n
• Ayuri's School Blouse with Bow - Red\n
• Ayuri's Tartan Skirt - Red\n
• Ayuri's Heeled Knee-High Boots - White\n
Put together an anime cosplay costume, or maybe just an outrageous outfit! Lockwood has all the finishing touches. [#Legal]</LANG>
    <LANG ID="zh-TW">Ayuri Mega Bundle\n\n 
This pack includes the following items: \n 
• The Ayuri\n
• Ayuri's Gothic Lolita Dress - Black\n
• Ayuri's School Blouse with Bow - Red\n
• Ayuri's Tartan Skirt - Red\n
• Ayuri's Heeled Knee-High Boots - White\n
Put together an anime cosplay costume, or maybe just an outrageous outfit! Lockwood has all the finishing touches. [#Legal]</LANG>
    <LANG ID="en-US">Ayuri Mega Bundle\n\n 
This pack includes the following items: \n 
• The Ayuri\n
• Ayuri's Gothic Lolita Dress - Black\n
• Ayuri's School Blouse with Bow - Red\n
• Ayuri's Tartan Skirt - Red\n
• Ayuri's Heeled Knee-High Boots - White\n
Put together an anime cosplay costume, or maybe just an outrageous outfit! Lockwood has all the finishing touches. [#Legal]</LANG>
  </PHRASE>
</LOCALISATION>