<?xml version="1.0" encoding="utf-8"?>
<LOCALISATION xmlns:xsi="http://www.w3.org/2001/XMLSchema-instance" xmlns:xs="http://www.w3.org/2001/XMLSchema" default_language="en-GB" xmlns="http://home.scedev.net/schema/object">
	<PHRASE>
		<LANG ID="REF">Open_Beta_Monument_Mini</LANG>
		<LANG ID="en-GB">Open Commemorative Object (mini)</LANG>
		<LANG ID="fr-FR">Open Commemorative Object (mini)</LANG>
		<LANG ID="de-DE">Open Commemorative Object (mini)</LANG>
		<LANG ID="it-IT">Open Commemorative Object (mini)</LANG>
		<LANG ID="es-ES">Open Commemorative Object (mini)</LANG>
		<LANG ID="ja-JP">オープン記念オブジェ（ミニ）</LANG>
		<LANG ID="ko-KR">오픈 기념 오브제 (미니)</LANG>
		<LANG ID="en-SG">Open Commemorative Object (mini)</LANG>
		<LANG ID="zh-HK">迷你公開紀念雕像</LANG>
		<LANG ID="zh-TW">迷你公開紀念雕像</LANG>
	</PHRASE>
	<PHRASE>
		<LANG ID="REF">description</LANG>
		<LANG ID="en-GB">Second User Awareness Survey Reward: 　　　　　　　 　　　　　   An Open Commemorative Object (mini)</LANG>
		<LANG ID="fr-FR">Second User Awareness Survey Reward: 　　　　　　　 　　　　　   An Open Commemorative Object (mini)</LANG>
		<LANG ID="de-DE">Second User Awareness Survey Reward: 　　　　　　　 　　　　　   An Open Commemorative Object (mini)</LANG>
		<LANG ID="it-IT">Second User Awareness Survey Reward: 　　　　　　　 　　　　　   An Open Commemorative Object (mini)</LANG>
		<LANG ID="es-ES">Second User Awareness Survey Reward: 　　　　　　　 　　　　　   An Open Commemorative Object (mini)</LANG>
		<LANG ID="ja-JP">第2回 ユーザー意識調査イベントリワード 　　　　　　　　　　　　　　　オープン記念オブジェのミニチュア</LANG>
		<LANG ID="ko-KR">제2회 유저 의식조사 이벤트 리워드  오픈 기념 오브제의 미니어처</LANG>
		<LANG ID="en-SG">Second User Awareness Survey Reward: 　　　　　　　 　　　　　   An Open Commemorative Object (mini)</LANG>
		<LANG ID="zh-HK">第2回 玩家意識調查活動獎品 迷你公開紀念雕像</LANG>
		<LANG ID="zh-TW">第2回 玩家意識調查活動獎品 迷你公開紀念雕像</LANG>
	</PHRASE>
</LOCALISATION>