<?xml version="1.0" encoding="utf-8"?>
<LOCALISATION xmlns:xsi="http://www.w3.org/2001/XMLSchema-instance" xmlns:xs="http://www.w3.org/2001/XMLSchema" default_language="ja-JP" xmlns="http://home.scedev.net/schema/object">
  <PHRASE>
    <LANG ID="REF">kName</LANG>
    <LANG ID="en-GB">Alien Headdress/Gold (Men)</LANG>
    <LANG ID="fr-FR">Coiffure d'extraterrestre/D'or (homme)</LANG>
    <LANG ID="de-DE">Alien-Maske/Gold (Herren)</LANG>
    <LANG ID="it-IT">Copricapo alieno/Oro (uomo)</LANG>
    <LANG ID="es-ES">Tocado de alienígena dorado (hombre)</LANG>
    <LANG ID="ja-JP">宇宙人のかぶりもの・ゴールド男性用</LANG>
    <LANG ID="ko-KR">Male01_Hat_AlienheadGold</LANG>
    <LANG ID="en-SG">Male01_Hat_AlienheadGold</LANG>
    <LANG ID="zh-HK">Male01_Hat_AlienheadGold</LANG>
    <LANG ID="zh-TW">Male01_Hat_AlienheadGold</LANG>
    <LANG ID="en-US">Alien Headdress/Gold (Men)</LANG>
  </PHRASE>
  <PHRASE>
    <LANG ID="REF">kDesc</LANG>
    <LANG ID="en-GB">Headdress which resembles a gold alien. For male.\nEquipping this item raises the amount of experience points gained while playing the Abduction Simulator.\n
The amount of experience gained increases with other same-valued items.[#Legal]</LANG>
    <LANG ID="fr-FR">Coiffure qui vous fait ressembler à un extraterrestre d'or. Pour homme.\nUtilisez-la pour augmenter l'expérience gagnée dans le simulateur d'enlèvement.\n Gagnez plus d'expérience en l'associant à d'autres objets offrant le même avantage.[#Legal]</LANG>
    <LANG ID="de-DE">Maske, die einen Golden Alien darstellt. Für Herren.\nErhöht deine im Entführungssimulator gewonnene Erfahrung.\n
Durch die Kombination weiterer Objekte desselben Werts, erhöht sich die Erfahrung noch mehr.[#Legal]</LANG>
    <LANG ID="it-IT">Copricapo per assomigliare ad un alieno Oro. Per uomo. \nUtilizzandolo, la quantità di punti esperienza guadagnati in Rapimento simulato aumenta. \n
Il guadagno di punti esperienza aumenta se combini oggetti dello stesso valore.[#Legal]</LANG>
    <LANG ID="es-ES">Tocado que parece un alienígena dorado. Para hombre.\nAl equiparlo, se incrementa la cantidad de experiencia que ganas en Abduction Simulator.\n
Si lo combinas con otros objetos que tengan el mismo valor, la experiencia se incrementa aún más.[#Legal]</LANG>
    <LANG ID="ja-JP">ゴールドの宇宙人を模したかぶりもの・男性用。\n装着しているとアブダクトシミュレーターに「獲得経験値UP」のボーナスが付きます。\n他の「獲得経験値UP」と組み合わせることでさらに獲得経験値にボーナスが付きます。[#Legal]</LANG>
    <LANG ID="ko-KR">ゴールドの宇宙人を模したかぶりもの・男性用。\n装着しているとアブダクトシミュレーターに「獲得経験値UP」のボーナスが付きます。\n他の「獲得経験値UP」と組み合わせることでさらに獲得経験値にボーナスが付きます。[#Legal]</LANG>
    <LANG ID="en-SG">ゴールドの宇宙人を模したかぶりもの・男性用。\n装着しているとアブダクトシミュレーターに「獲得経験値UP」のボーナスが付きます。\n他の「獲得経験値UP」と組み合わせることでさらに獲得経験値にボーナスが付きます。[#Legal]</LANG>
    <LANG ID="zh-HK">ゴールドの宇宙人を模したかぶりもの・男性用。\n装着しているとアブダクトシミュレーターに「獲得経験値UP」のボーナスが付きます。\n他の「獲得経験値UP」と組み合わせることでさらに獲得経験値にボーナスが付きます。[#Legal]</LANG>
    <LANG ID="zh-TW">ゴールドの宇宙人を模したかぶりもの・男性用。\n装着しているとアブダクトシミュレーターに「獲得経験値UP」のボーナスが付きます。\n他の「獲得経験値UP」と組み合わせることでさらに獲得経験値にボーナスが付きます。[#Legal]</LANG>
    <LANG ID="en-US">Headdress which resembles a gold alien. For male.\nEquipping this item raises the amount of experience points gained while playing the Abduction Simulator.\nThe amount of experience gained increases with other same-valued items.[#Legal]</LANG>
  </PHRASE>
</LOCALISATION>