<?xml version="1.0" encoding="utf-8"?>
<LOCALISATION xmlns:xsi="http://www.w3.org/2001/XMLSchema-instance" xmlns:xs="http://www.w3.org/2001/XMLSchema" default_language="en-GB" xmlns="http://home.scedev.net/schema/object">
  <PHRASE>
    <LANG ID="REF">kName</LANG>
    <LANG ID="en-GB">Pixel Invader Hooded Sweatshirt</LANG>
    <LANG ID="fr-FR">Envahisseur Pixel Sweatshirt Encapuchonné</LANG>
    <LANG ID="de-DE">Pixel Invader Verdecktes Sweatshirt</LANG>
    <LANG ID="it-IT">Invasore Pixellato Felpa Incappucciata</LANG>
    <LANG ID="es-ES">Pixel Invasor Sudadera Encapuchada</LANG>
  </PHRASE>
  <PHRASE>
    <LANG ID="REF">kDesc</LANG>
    <LANG ID="en-GB">Red pixel invader hooded sweatshirt  [#Legal]</LANG>
    <LANG ID="fr-FR">Envahisseur pixel rouge sweatshirt encapuchonné  [#Legal]</LANG>
    <LANG ID="de-DE">Pixel Invader - rot verdecktes sweatshirt  [#Legal]</LANG>
    <LANG ID="it-IT">Invasore pixellato rosso felpa incappucciata  [#Legal]</LANG>
    <LANG ID="es-ES">Píxel invasor rojo sudadera encapuchada  [#Legal]</LANG>
  </PHRASE>
</LOCALISATION>