<?xml version="1.0" encoding="utf-8"?>
<LOCALISATION xmlns:xsi="http://www.w3.org/2001/XMLSchema-instance" xmlns:xs="http://www.w3.org/2001/XMLSchema" default_language="en-GB" xmlns="http://home.scedev.net/schema/object">
  <PHRASE>
    <LANG ID="REF">kName</LANG>
    <LANG ID="en-GB">網</LANG>
    <LANG ID="fr-FR">網</LANG>
    <LANG ID="de-DE">網</LANG>
    <LANG ID="it-IT">網</LANG>
    <LANG ID="es-ES">網</LANG>
    <LANG ID="ja-JP">網</LANG>
    <LANG ID="ko-KR">網</LANG>
    <LANG ID="en-SG">網</LANG>
    <LANG ID="zh-HK">網</LANG>
    <LANG ID="zh-TW">網</LANG>
    <LANG ID="en-US">網</LANG>
  </PHRASE>
  <PHRASE>
    <LANG ID="REF">kDesc</LANG>
    <LANG ID="en-GB">*Not Localized* Object Description</LANG>
    <LANG ID="fr-FR">*Not Localized* Object Description</LANG>
    <LANG ID="de-DE">*Not Localized* Object Description</LANG>
    <LANG ID="it-IT">*Not Localized* Object Description</LANG>
    <LANG ID="es-ES">*Not Localized* Object Description</LANG>
    <LANG ID="ja-JP">ガイコツ船長</LANG>
    <LANG ID="ko-KR">*Not Localized* Object Description</LANG>
    <LANG ID="en-SG">*Not Localized* Object Description</LANG>
    <LANG ID="zh-HK">*Not Localized* Object Description</LANG>
    <LANG ID="zh-TW">*Not Localized* Object Description</LANG>
    <LANG ID="en-US">*Not Localized* Object Description</LANG>
  </PHRASE>
  <PHRASE>
    <LANG ID="REF">WndMessageDialog Navi Close</LANG>
    <LANG ID="en-GB">[CROSS]:OK</LANG>
    <LANG ID="fr-FR">[CROSS]:OK</LANG>
    <LANG ID="de-DE">[CROSS]:OK</LANG>
    <LANG ID="it-IT">[CROSS]:OK</LANG>
    <LANG ID="es-ES">[CROSS]:OK</LANG>
    <LANG ID="ja-JP">[CROSS]:OK</LANG>
    <LANG ID="ko-KR">[CROSS]:OK</LANG>
    <LANG ID="en-SG">[CROSS]:OK</LANG>
    <LANG ID="zh-HK">[CROSS]:OK</LANG>
    <LANG ID="zh-TW">[CROSS]:OK</LANG>
    <LANG ID="en-US">[CROSS]:OK</LANG>
  </PHRASE>
  <PHRASE>
    <LANG ID="REF">WndSimpleMenuDialog Navi</LANG>
    <LANG ID="en-GB">[UP][DOWN]:Move cursor [CROSS]:Select</LANG>
    <LANG ID="fr-FR">[UP][DOWN]: Bougez le curseur [CROSS]:Sélectionner</LANG>
    <LANG ID="de-DE">[UP][DOWN]:Cursor bewegen [CROSS]:Auswahl</LANG>
    <LANG ID="it-IT">[UP][DOWN]: muove cursore [CROSS]: seleziona</LANG>
    <LANG ID="es-ES">[ARRIBA][ABAJO]:Mover cursor [CRUZ]:Seleccionar</LANG>
    <LANG ID="ja-JP">[UP][DOWN]:選択 [CROSS]:決定</LANG>
    <LANG ID="ko-KR">[UP][DOWN]:선택 [CROSS]:결정</LANG>
    <LANG ID="en-SG">[UP][DOWN]:Select [CROSS]:Confirm</LANG>
    <LANG ID="zh-HK">[UP][DOWN]：選擇 [CROSS]：決定</LANG>
    <LANG ID="zh-TW">[UP][DOWN]：選擇 [CROSS]：決定</LANG>
    <LANG ID="en-US">[UP][DOWN]:Move cursor [CROSS]:Select</LANG>
  </PHRASE>
  <PHRASE>
    <LANG ID="REF">APR_TAB_CAPTAIN</LANG>
    <LANG ID="en-GB">*Not Localized* Object Description</LANG>
    <LANG ID="fr-FR">*Not Localized* Object Description</LANG>
    <LANG ID="de-DE">*Not Localized* Object Description</LANG>
    <LANG ID="it-IT">*Not Localized* Object Description</LANG>
    <LANG ID="es-ES">*Not Localized* Object Description</LANG>
    <LANG ID="ja-JP">ガイコツ船長</LANG>
    <LANG ID="ko-KR">*Not Localized* Object Description</LANG>
    <LANG ID="en-SG">*Not Localized* Object Description</LANG>
    <LANG ID="zh-HK">*Not Localized* Object Description</LANG>
    <LANG ID="zh-TW">*Not Localized* Object Description</LANG>
    <LANG ID="en-US">*Not Localized* Object Description</LANG>
  </PHRASE>
  <PHRASE>
    <LANG ID="REF">NORM_001</LANG>
    <LANG ID="en-GB">*Not Localized* Object Description</LANG>
    <LANG ID="fr-FR">*Not Localized* Object Description</LANG>
    <LANG ID="de-DE">*Not Localized* Object Description</LANG>
    <LANG ID="it-IT">*Not Localized* Object Description</LANG>
    <LANG ID="es-ES">*Not Localized* Object Description</LANG>
    <LANG ID="ja-JP">網が張ってある\n外へは出られそうにない</LANG>
    <LANG ID="ko-KR">*Not Localized* Object Description</LANG>
    <LANG ID="en-SG">*Not Localized* Object Description</LANG>
    <LANG ID="zh-HK">*Not Localized* Object Description</LANG>
    <LANG ID="zh-TW">*Not Localized* Object Description</LANG>
    <LANG ID="en-US">*Not Localized* Object Description</LANG>
  </PHRASE>
  <PHRASE>
    <LANG ID="REF">APR_001_1</LANG>
    <LANG ID="en-GB">*Not Localized* Object Description</LANG>
    <LANG ID="fr-FR">*Not Localized* Object Description</LANG>
    <LANG ID="de-DE">*Not Localized* Object Description</LANG>
    <LANG ID="it-IT">*Not Localized* Object Description</LANG>
    <LANG ID="es-ES">*Not Localized* Object Description</LANG>
    <LANG ID="ja-JP">無念じゃ…</LANG>
    <LANG ID="ko-KR">*Not Localized* Object Description</LANG>
    <LANG ID="en-SG">*Not Localized* Object Description</LANG>
    <LANG ID="zh-HK">*Not Localized* Object Description</LANG>
    <LANG ID="zh-TW">*Not Localized* Object Description</LANG>
    <LANG ID="en-US">*Not Localized* Object Description</LANG>
  </PHRASE>
  <PHRASE>
    <LANG ID="REF">APR_001_2</LANG>
    <LANG ID="en-GB">*Not Localized* Object Description</LANG>
    <LANG ID="fr-FR">*Not Localized* Object Description</LANG>
    <LANG ID="de-DE">*Not Localized* Object Description</LANG>
    <LANG ID="it-IT">*Not Localized* Object Description</LANG>
    <LANG ID="es-ES">*Not Localized* Object Description</LANG>
    <LANG ID="ja-JP">あんな奴のニセ情報に騙されて\n大切な船をこの入り江に入れたばっかりに\n船が…　わしの大切な船があんな無残にも壊れてしまった…</LANG>
    <LANG ID="ko-KR">*Not Localized* Object Description</LANG>
    <LANG ID="en-SG">*Not Localized* Object Description</LANG>
    <LANG ID="zh-HK">*Not Localized* Object Description</LANG>
    <LANG ID="zh-TW">*Not Localized* Object Description</LANG>
    <LANG ID="en-US">*Not Localized* Object Description</LANG>
  </PHRASE>
  <PHRASE>
    <LANG ID="REF">APR_001_3</LANG>
    <LANG ID="en-GB">*Not Localized* Object Description</LANG>
    <LANG ID="fr-FR">*Not Localized* Object Description</LANG>
    <LANG ID="de-DE">*Not Localized* Object Description</LANG>
    <LANG ID="it-IT">*Not Localized* Object Description</LANG>
    <LANG ID="es-ES">*Not Localized* Object Description</LANG>
    <LANG ID="ja-JP">ふむ？\nお前、わしの話を聞いていたな？</LANG>
    <LANG ID="ko-KR">*Not Localized* Object Description</LANG>
    <LANG ID="en-SG">*Not Localized* Object Description</LANG>
    <LANG ID="zh-HK">*Not Localized* Object Description</LANG>
    <LANG ID="zh-TW">*Not Localized* Object Description</LANG>
    <LANG ID="en-US">*Not Localized* Object Description</LANG>
  </PHRASE>
  <PHRASE>
    <LANG ID="REF">APR_001_3_A</LANG>
    <LANG ID="en-GB">*Not Localized* Object Description</LANG>
    <LANG ID="fr-FR">*Not Localized* Object Description</LANG>
    <LANG ID="de-DE">*Not Localized* Object Description</LANG>
    <LANG ID="it-IT">*Not Localized* Object Description</LANG>
    <LANG ID="es-ES">*Not Localized* Object Description</LANG>
    <LANG ID="ja-JP">はい、聞きました　と正直に言う</LANG>
    <LANG ID="ko-KR">*Not Localized* Object Description</LANG>
    <LANG ID="en-SG">*Not Localized* Object Description</LANG>
    <LANG ID="zh-HK">*Not Localized* Object Description</LANG>
    <LANG ID="zh-TW">*Not Localized* Object Description</LANG>
    <LANG ID="en-US">*Not Localized* Object Description</LANG>
  </PHRASE>
  <PHRASE>
    <LANG ID="REF">APR_001_3_B</LANG>
    <LANG ID="en-GB">*Not Localized* Object Description</LANG>
    <LANG ID="fr-FR">*Not Localized* Object Description</LANG>
    <LANG ID="de-DE">*Not Localized* Object Description</LANG>
    <LANG ID="it-IT">*Not Localized* Object Description</LANG>
    <LANG ID="es-ES">*Not Localized* Object Description</LANG>
    <LANG ID="ja-JP">うっかり聞いてしまいました　と白状する</LANG>
    <LANG ID="ko-KR">*Not Localized* Object Description</LANG>
    <LANG ID="en-SG">*Not Localized* Object Description</LANG>
    <LANG ID="zh-HK">*Not Localized* Object Description</LANG>
    <LANG ID="zh-TW">*Not Localized* Object Description</LANG>
    <LANG ID="en-US">*Not Localized* Object Description</LANG>
  </PHRASE>
  <PHRASE>
    <LANG ID="REF">APR_001_3_C</LANG>
    <LANG ID="en-GB">*Not Localized* Object Description</LANG>
    <LANG ID="fr-FR">*Not Localized* Object Description</LANG>
    <LANG ID="de-DE">*Not Localized* Object Description</LANG>
    <LANG ID="it-IT">*Not Localized* Object Description</LANG>
    <LANG ID="es-ES">*Not Localized* Object Description</LANG>
    <LANG ID="ja-JP">騙されて船が壊れた事は聞いてない　とウソをつく</LANG>
    <LANG ID="ko-KR">*Not Localized* Object Description</LANG>
    <LANG ID="en-SG">*Not Localized* Object Description</LANG>
    <LANG ID="zh-HK">*Not Localized* Object Description</LANG>
    <LANG ID="zh-TW">*Not Localized* Object Description</LANG>
    <LANG ID="en-US">*Not Localized* Object Description</LANG>
  </PHRASE>
  <PHRASE>
    <LANG ID="REF">APR_001_3_D</LANG>
    <LANG ID="en-GB">*Not Localized* Object Description</LANG>
    <LANG ID="fr-FR">*Not Localized* Object Description</LANG>
    <LANG ID="de-DE">*Not Localized* Object Description</LANG>
    <LANG ID="it-IT">*Not Localized* Object Description</LANG>
    <LANG ID="es-ES">*Not Localized* Object Description</LANG>
    <LANG ID="ja-JP">よく聞き取れなかったのでもう一度お願いします</LANG>
    <LANG ID="ko-KR">*Not Localized* Object Description</LANG>
    <LANG ID="en-SG">*Not Localized* Object Description</LANG>
    <LANG ID="zh-HK">*Not Localized* Object Description</LANG>
    <LANG ID="zh-TW">*Not Localized* Object Description</LANG>
    <LANG ID="en-US">*Not Localized* Object Description</LANG>
  </PHRASE>
  <PHRASE>
    <LANG ID="REF">APR_001_4</LANG>
    <LANG ID="en-GB">*Not Localized* Object Description</LANG>
    <LANG ID="fr-FR">*Not Localized* Object Description</LANG>
    <LANG ID="de-DE">*Not Localized* Object Description</LANG>
    <LANG ID="it-IT">*Not Localized* Object Description</LANG>
    <LANG ID="es-ES">*Not Localized* Object Description</LANG>
    <LANG ID="ja-JP">はい、聞きました</LANG>
    <LANG ID="ko-KR">*Not Localized* Object Description</LANG>
    <LANG ID="en-SG">*Not Localized* Object Description</LANG>
    <LANG ID="zh-HK">*Not Localized* Object Description</LANG>
    <LANG ID="zh-TW">*Not Localized* Object Description</LANG>
    <LANG ID="en-US">*Not Localized* Object Description</LANG>
  </PHRASE>
  <PHRASE>
    <LANG ID="REF">APR_001_5</LANG>
    <LANG ID="en-GB">*Not Localized* Object Description</LANG>
    <LANG ID="fr-FR">*Not Localized* Object Description</LANG>
    <LANG ID="de-DE">*Not Localized* Object Description</LANG>
    <LANG ID="it-IT">*Not Localized* Object Description</LANG>
    <LANG ID="es-ES">*Not Localized* Object Description</LANG>
    <LANG ID="ja-JP">そうか…</LANG>
    <LANG ID="ko-KR">*Not Localized* Object Description</LANG>
    <LANG ID="en-SG">*Not Localized* Object Description</LANG>
    <LANG ID="zh-HK">*Not Localized* Object Description</LANG>
    <LANG ID="zh-TW">*Not Localized* Object Description</LANG>
    <LANG ID="en-US">*Not Localized* Object Description</LANG>
  </PHRASE>
  <PHRASE>
    <LANG ID="REF">APR_001_6</LANG>
    <LANG ID="en-GB">*Not Localized* Object Description</LANG>
    <LANG ID="fr-FR">*Not Localized* Object Description</LANG>
    <LANG ID="de-DE">*Not Localized* Object Description</LANG>
    <LANG ID="it-IT">*Not Localized* Object Description</LANG>
    <LANG ID="es-ES">*Not Localized* Object Description</LANG>
    <LANG ID="ja-JP">すみません、うっかり聞いてしまいました</LANG>
    <LANG ID="ko-KR">*Not Localized* Object Description</LANG>
    <LANG ID="en-SG">*Not Localized* Object Description</LANG>
    <LANG ID="zh-HK">*Not Localized* Object Description</LANG>
    <LANG ID="zh-TW">*Not Localized* Object Description</LANG>
    <LANG ID="en-US">*Not Localized* Object Description</LANG>
  </PHRASE>
  <PHRASE>
    <LANG ID="REF">APR_001_7</LANG>
    <LANG ID="en-GB">*Not Localized* Object Description</LANG>
    <LANG ID="fr-FR">*Not Localized* Object Description</LANG>
    <LANG ID="de-DE">*Not Localized* Object Description</LANG>
    <LANG ID="it-IT">*Not Localized* Object Description</LANG>
    <LANG ID="es-ES">*Not Localized* Object Description</LANG>
    <LANG ID="ja-JP">そうか…</LANG>
    <LANG ID="ko-KR">*Not Localized* Object Description</LANG>
    <LANG ID="en-SG">*Not Localized* Object Description</LANG>
    <LANG ID="zh-HK">*Not Localized* Object Description</LANG>
    <LANG ID="zh-TW">*Not Localized* Object Description</LANG>
    <LANG ID="en-US">*Not Localized* Object Description</LANG>
  </PHRASE>
  <PHRASE>
    <LANG ID="REF">APR_001_8</LANG>
    <LANG ID="en-GB">*Not Localized* Object Description</LANG>
    <LANG ID="fr-FR">*Not Localized* Object Description</LANG>
    <LANG ID="de-DE">*Not Localized* Object Description</LANG>
    <LANG ID="it-IT">*Not Localized* Object Description</LANG>
    <LANG ID="es-ES">*Not Localized* Object Description</LANG>
    <LANG ID="ja-JP">騙されて船が壊れたことなど聞いていない</LANG>
    <LANG ID="ko-KR">*Not Localized* Object Description</LANG>
    <LANG ID="en-SG">*Not Localized* Object Description</LANG>
    <LANG ID="zh-HK">*Not Localized* Object Description</LANG>
    <LANG ID="zh-TW">*Not Localized* Object Description</LANG>
    <LANG ID="en-US">*Not Localized* Object Description</LANG>
  </PHRASE>
  <PHRASE>
    <LANG ID="REF">APR_001_9</LANG>
    <LANG ID="en-GB">*Not Localized* Object Description</LANG>
    <LANG ID="fr-FR">*Not Localized* Object Description</LANG>
    <LANG ID="de-DE">*Not Localized* Object Description</LANG>
    <LANG ID="it-IT">*Not Localized* Object Description</LANG>
    <LANG ID="es-ES">*Not Localized* Object Description</LANG>
    <LANG ID="ja-JP">ちゃんと聞いているではないか！</LANG>
    <LANG ID="ko-KR">*Not Localized* Object Description</LANG>
    <LANG ID="en-SG">*Not Localized* Object Description</LANG>
    <LANG ID="zh-HK">*Not Localized* Object Description</LANG>
    <LANG ID="zh-TW">*Not Localized* Object Description</LANG>
    <LANG ID="en-US">*Not Localized* Object Description</LANG>
  </PHRASE>
  <PHRASE>
    <LANG ID="REF">APR_001_10</LANG>
    <LANG ID="en-GB">*Not Localized* Object Description</LANG>
    <LANG ID="fr-FR">*Not Localized* Object Description</LANG>
    <LANG ID="de-DE">*Not Localized* Object Description</LANG>
    <LANG ID="it-IT">*Not Localized* Object Description</LANG>
    <LANG ID="es-ES">*Not Localized* Object Description</LANG>
    <LANG ID="ja-JP">よく聞き取れなかったのでもう一度お願いします</LANG>
    <LANG ID="ko-KR">*Not Localized* Object Description</LANG>
    <LANG ID="en-SG">*Not Localized* Object Description</LANG>
    <LANG ID="zh-HK">*Not Localized* Object Description</LANG>
    <LANG ID="zh-TW">*Not Localized* Object Description</LANG>
    <LANG ID="en-US">*Not Localized* Object Description</LANG>
  </PHRASE>
  <PHRASE>
    <LANG ID="REF">APR_001_11</LANG>
    <LANG ID="en-GB">*Not Localized* Object Description</LANG>
    <LANG ID="fr-FR">*Not Localized* Object Description</LANG>
    <LANG ID="de-DE">*Not Localized* Object Description</LANG>
    <LANG ID="it-IT">*Not Localized* Object Description</LANG>
    <LANG ID="es-ES">*Not Localized* Object Description</LANG>
    <LANG ID="ja-JP">何？\nそう言うなら話してやろう</LANG>
    <LANG ID="ko-KR">*Not Localized* Object Description</LANG>
    <LANG ID="en-SG">*Not Localized* Object Description</LANG>
    <LANG ID="zh-HK">*Not Localized* Object Description</LANG>
    <LANG ID="zh-TW">*Not Localized* Object Description</LANG>
    <LANG ID="en-US">*Not Localized* Object Description</LANG>
  </PHRASE>
  <PHRASE>
    <LANG ID="REF">APR_001_12</LANG>
    <LANG ID="en-GB">*Not Localized* Object Description</LANG>
    <LANG ID="fr-FR">*Not Localized* Object Description</LANG>
    <LANG ID="de-DE">*Not Localized* Object Description</LANG>
    <LANG ID="it-IT">*Not Localized* Object Description</LANG>
    <LANG ID="es-ES">*Not Localized* Object Description</LANG>
    <LANG ID="ja-JP">わしは、ジュニパーベリィ号の船長だったのだ</LANG>
    <LANG ID="ko-KR">*Not Localized* Object Description</LANG>
    <LANG ID="en-SG">*Not Localized* Object Description</LANG>
    <LANG ID="zh-HK">*Not Localized* Object Description</LANG>
    <LANG ID="zh-TW">*Not Localized* Object Description</LANG>
    <LANG ID="en-US">*Not Localized* Object Description</LANG>
  </PHRASE>
  <PHRASE>
    <LANG ID="REF">APR_001_13</LANG>
    <LANG ID="en-GB">*Not Localized* Object Description</LANG>
    <LANG ID="fr-FR">*Not Localized* Object Description</LANG>
    <LANG ID="de-DE">*Not Localized* Object Description</LANG>
    <LANG ID="it-IT">*Not Localized* Object Description</LANG>
    <LANG ID="es-ES">*Not Localized* Object Description</LANG>
    <LANG ID="ja-JP">荷物を運んで航海していたのだが、突然天候が崩れ\n風雨がしのげる安全な場所を探していたのだ</LANG>
    <LANG ID="ko-KR">*Not Localized* Object Description</LANG>
    <LANG ID="en-SG">*Not Localized* Object Description</LANG>
    <LANG ID="zh-HK">*Not Localized* Object Description</LANG>
    <LANG ID="zh-TW">*Not Localized* Object Description</LANG>
    <LANG ID="en-US">*Not Localized* Object Description</LANG>
  </PHRASE>
  <PHRASE>
    <LANG ID="REF">APR_001_14</LANG>
    <LANG ID="en-GB">*Not Localized* Object Description</LANG>
    <LANG ID="fr-FR">*Not Localized* Object Description</LANG>
    <LANG ID="de-DE">*Not Localized* Object Description</LANG>
    <LANG ID="it-IT">*Not Localized* Object Description</LANG>
    <LANG ID="es-ES">*Not Localized* Object Description</LANG>
    <LANG ID="ja-JP">すると船員のキースが、このエリアが安全なはずだ\nと言い出した\nわしはキースの言葉を信じて、\n船をこの入り江に入れたのだ</LANG>
    <LANG ID="ko-KR">*Not Localized* Object Description</LANG>
    <LANG ID="en-SG">*Not Localized* Object Description</LANG>
    <LANG ID="zh-HK">*Not Localized* Object Description</LANG>
    <LANG ID="zh-TW">*Not Localized* Object Description</LANG>
    <LANG ID="en-US">*Not Localized* Object Description</LANG>
  </PHRASE>
  <PHRASE>
    <LANG ID="REF">APR_001_15</LANG>
    <LANG ID="en-GB">*Not Localized* Object Description</LANG>
    <LANG ID="fr-FR">*Not Localized* Object Description</LANG>
    <LANG ID="de-DE">*Not Localized* Object Description</LANG>
    <LANG ID="it-IT">*Not Localized* Object Description</LANG>
    <LANG ID="es-ES">*Not Localized* Object Description</LANG>
    <LANG ID="ja-JP">ところが入り江に入れると\n突然、巨大な海竜が船を襲ってきて…\n船は無残な姿に…　無念じゃ…</LANG>
    <LANG ID="ko-KR">*Not Localized* Object Description</LANG>
    <LANG ID="en-SG">*Not Localized* Object Description</LANG>
    <LANG ID="zh-HK">*Not Localized* Object Description</LANG>
    <LANG ID="zh-TW">*Not Localized* Object Description</LANG>
    <LANG ID="en-US">*Not Localized* Object Description</LANG>
  </PHRASE>
  <PHRASE>
    <LANG ID="REF">APR_001_16</LANG>
    <LANG ID="en-GB">*Not Localized* Object Description</LANG>
    <LANG ID="fr-FR">*Not Localized* Object Description</LANG>
    <LANG ID="de-DE">*Not Localized* Object Description</LANG>
    <LANG ID="it-IT">*Not Localized* Object Description</LANG>
    <LANG ID="es-ES">*Not Localized* Object Description</LANG>
    <LANG ID="ja-JP">わしは、ウソをついて\n船をこの入り江に誘導したキースがにくい</LANG>
    <LANG ID="ko-KR">*Not Localized* Object Description</LANG>
    <LANG ID="en-SG">*Not Localized* Object Description</LANG>
    <LANG ID="zh-HK">*Not Localized* Object Description</LANG>
    <LANG ID="zh-TW">*Not Localized* Object Description</LANG>
    <LANG ID="en-US">*Not Localized* Object Description</LANG>
  </PHRASE>
  <PHRASE>
    <LANG ID="REF">APR_001_17</LANG>
    <LANG ID="en-GB">*Not Localized* Object Description</LANG>
    <LANG ID="fr-FR">*Not Localized* Object Description</LANG>
    <LANG ID="de-DE">*Not Localized* Object Description</LANG>
    <LANG ID="it-IT">*Not Localized* Object Description</LANG>
    <LANG ID="es-ES">*Not Localized* Object Description</LANG>
    <LANG ID="ja-JP">そうだ、キースはまだ船にいるはずだ\nお前、わしの無念をヤツに伝えてくれ</LANG>
    <LANG ID="ko-KR">*Not Localized* Object Description</LANG>
    <LANG ID="en-SG">*Not Localized* Object Description</LANG>
    <LANG ID="zh-HK">*Not Localized* Object Description</LANG>
    <LANG ID="zh-TW">*Not Localized* Object Description</LANG>
    <LANG ID="en-US">*Not Localized* Object Description</LANG>
  </PHRASE>
  <PHRASE>
    <LANG ID="REF">APR_001_17_A</LANG>
    <LANG ID="en-GB">*Not Localized* Object Description</LANG>
    <LANG ID="fr-FR">*Not Localized* Object Description</LANG>
    <LANG ID="de-DE">*Not Localized* Object Description</LANG>
    <LANG ID="it-IT">*Not Localized* Object Description</LANG>
    <LANG ID="es-ES">*Not Localized* Object Description</LANG>
    <LANG ID="ja-JP">わかりました　キースに伝えよう</LANG>
    <LANG ID="ko-KR">*Not Localized* Object Description</LANG>
    <LANG ID="en-SG">*Not Localized* Object Description</LANG>
    <LANG ID="zh-HK">*Not Localized* Object Description</LANG>
    <LANG ID="zh-TW">*Not Localized* Object Description</LANG>
    <LANG ID="en-US">*Not Localized* Object Description</LANG>
  </PHRASE>
  <PHRASE>
    <LANG ID="REF">APR_001_17_B</LANG>
    <LANG ID="en-GB">*Not Localized* Object Description</LANG>
    <LANG ID="fr-FR">*Not Localized* Object Description</LANG>
    <LANG ID="de-DE">*Not Localized* Object Description</LANG>
    <LANG ID="it-IT">*Not Localized* Object Description</LANG>
    <LANG ID="es-ES">*Not Localized* Object Description</LANG>
    <LANG ID="ja-JP">私には係わり合いのないことです</LANG>
    <LANG ID="ko-KR">*Not Localized* Object Description</LANG>
    <LANG ID="en-SG">*Not Localized* Object Description</LANG>
    <LANG ID="zh-HK">*Not Localized* Object Description</LANG>
    <LANG ID="zh-TW">*Not Localized* Object Description</LANG>
    <LANG ID="en-US">*Not Localized* Object Description</LANG>
  </PHRASE>
  <PHRASE>
    <LANG ID="REF">APR_001_17_C</LANG>
    <LANG ID="en-GB">*Not Localized* Object Description</LANG>
    <LANG ID="fr-FR">*Not Localized* Object Description</LANG>
    <LANG ID="de-DE">*Not Localized* Object Description</LANG>
    <LANG ID="it-IT">*Not Localized* Object Description</LANG>
    <LANG ID="es-ES">*Not Localized* Object Description</LANG>
    <LANG ID="ja-JP">伝えたら何かくれますか？</LANG>
    <LANG ID="ko-KR">*Not Localized* Object Description</LANG>
    <LANG ID="en-SG">*Not Localized* Object Description</LANG>
    <LANG ID="zh-HK">*Not Localized* Object Description</LANG>
    <LANG ID="zh-TW">*Not Localized* Object Description</LANG>
    <LANG ID="en-US">*Not Localized* Object Description</LANG>
  </PHRASE>
  <PHRASE>
    <LANG ID="REF">APR_001_17_D</LANG>
    <LANG ID="en-GB">*Not Localized* Object Description</LANG>
    <LANG ID="fr-FR">*Not Localized* Object Description</LANG>
    <LANG ID="de-DE">*Not Localized* Object Description</LANG>
    <LANG ID="it-IT">*Not Localized* Object Description</LANG>
    <LANG ID="es-ES">*Not Localized* Object Description</LANG>
    <LANG ID="ja-JP">うるさいこのガイコツ野郎め！</LANG>
    <LANG ID="ko-KR">*Not Localized* Object Description</LANG>
    <LANG ID="en-SG">*Not Localized* Object Description</LANG>
    <LANG ID="zh-HK">*Not Localized* Object Description</LANG>
    <LANG ID="zh-TW">*Not Localized* Object Description</LANG>
    <LANG ID="en-US">*Not Localized* Object Description</LANG>
  </PHRASE>
  <PHRASE>
    <LANG ID="REF">APR_001_18</LANG>
    <LANG ID="en-GB">*Not Localized* Object Description</LANG>
    <LANG ID="fr-FR">*Not Localized* Object Description</LANG>
    <LANG ID="de-DE">*Not Localized* Object Description</LANG>
    <LANG ID="it-IT">*Not Localized* Object Description</LANG>
    <LANG ID="es-ES">*Not Localized* Object Description</LANG>
    <LANG ID="ja-JP">わかりました　キースに伝えよう</LANG>
    <LANG ID="ko-KR">*Not Localized* Object Description</LANG>
    <LANG ID="en-SG">*Not Localized* Object Description</LANG>
    <LANG ID="zh-HK">*Not Localized* Object Description</LANG>
    <LANG ID="zh-TW">*Not Localized* Object Description</LANG>
    <LANG ID="en-US">*Not Localized* Object Description</LANG>
  </PHRASE>
  <PHRASE>
    <LANG ID="REF">APR_001_19</LANG>
    <LANG ID="en-GB">*Not Localized* Object Description</LANG>
    <LANG ID="fr-FR">*Not Localized* Object Description</LANG>
    <LANG ID="de-DE">*Not Localized* Object Description</LANG>
    <LANG ID="it-IT">*Not Localized* Object Description</LANG>
    <LANG ID="es-ES">*Not Localized* Object Description</LANG>
    <LANG ID="ja-JP">頼んだぞ\nわしの無念を伝えてくれよ</LANG>
    <LANG ID="ko-KR">*Not Localized* Object Description</LANG>
    <LANG ID="en-SG">*Not Localized* Object Description</LANG>
    <LANG ID="zh-HK">*Not Localized* Object Description</LANG>
    <LANG ID="zh-TW">*Not Localized* Object Description</LANG>
    <LANG ID="en-US">*Not Localized* Object Description</LANG>
  </PHRASE>
  <PHRASE>
    <LANG ID="REF">APR_001_20</LANG>
    <LANG ID="en-GB">*Not Localized* Object Description</LANG>
    <LANG ID="fr-FR">*Not Localized* Object Description</LANG>
    <LANG ID="de-DE">*Not Localized* Object Description</LANG>
    <LANG ID="it-IT">*Not Localized* Object Description</LANG>
    <LANG ID="es-ES">*Not Localized* Object Description</LANG>
    <LANG ID="ja-JP">私には係わり合いのないことです</LANG>
    <LANG ID="ko-KR">*Not Localized* Object Description</LANG>
    <LANG ID="en-SG">*Not Localized* Object Description</LANG>
    <LANG ID="zh-HK">*Not Localized* Object Description</LANG>
    <LANG ID="zh-TW">*Not Localized* Object Description</LANG>
    <LANG ID="en-US">*Not Localized* Object Description</LANG>
  </PHRASE>
  <PHRASE>
    <LANG ID="REF">APR_001_21</LANG>
    <LANG ID="en-GB">*Not Localized* Object Description</LANG>
    <LANG ID="fr-FR">*Not Localized* Object Description</LANG>
    <LANG ID="de-DE">*Not Localized* Object Description</LANG>
    <LANG ID="it-IT">*Not Localized* Object Description</LANG>
    <LANG ID="es-ES">*Not Localized* Object Description</LANG>
    <LANG ID="ja-JP">そんなこと言わずに\nキースにわしの無念を伝えてくれ</LANG>
    <LANG ID="ko-KR">*Not Localized* Object Description</LANG>
    <LANG ID="en-SG">*Not Localized* Object Description</LANG>
    <LANG ID="zh-HK">*Not Localized* Object Description</LANG>
    <LANG ID="zh-TW">*Not Localized* Object Description</LANG>
    <LANG ID="en-US">*Not Localized* Object Description</LANG>
  </PHRASE>
  <PHRASE>
    <LANG ID="REF">APR_001_22</LANG>
    <LANG ID="en-GB">*Not Localized* Object Description</LANG>
    <LANG ID="fr-FR">*Not Localized* Object Description</LANG>
    <LANG ID="de-DE">*Not Localized* Object Description</LANG>
    <LANG ID="it-IT">*Not Localized* Object Description</LANG>
    <LANG ID="es-ES">*Not Localized* Object Description</LANG>
    <LANG ID="ja-JP">頼んだぞ</LANG>
    <LANG ID="ko-KR">*Not Localized* Object Description</LANG>
    <LANG ID="en-SG">*Not Localized* Object Description</LANG>
    <LANG ID="zh-HK">*Not Localized* Object Description</LANG>
    <LANG ID="zh-TW">*Not Localized* Object Description</LANG>
    <LANG ID="en-US">*Not Localized* Object Description</LANG>
  </PHRASE>
  <PHRASE>
    <LANG ID="REF">APR_001_23</LANG>
    <LANG ID="en-GB">*Not Localized* Object Description</LANG>
    <LANG ID="fr-FR">*Not Localized* Object Description</LANG>
    <LANG ID="de-DE">*Not Localized* Object Description</LANG>
    <LANG ID="it-IT">*Not Localized* Object Description</LANG>
    <LANG ID="es-ES">*Not Localized* Object Description</LANG>
    <LANG ID="ja-JP">伝えたら何かくれますか？</LANG>
    <LANG ID="ko-KR">*Not Localized* Object Description</LANG>
    <LANG ID="en-SG">*Not Localized* Object Description</LANG>
    <LANG ID="zh-HK">*Not Localized* Object Description</LANG>
    <LANG ID="zh-TW">*Not Localized* Object Description</LANG>
    <LANG ID="en-US">*Not Localized* Object Description</LANG>
  </PHRASE>
  <PHRASE>
    <LANG ID="REF">APR_001_24</LANG>
    <LANG ID="en-GB">*Not Localized* Object Description</LANG>
    <LANG ID="fr-FR">*Not Localized* Object Description</LANG>
    <LANG ID="de-DE">*Not Localized* Object Description</LANG>
    <LANG ID="it-IT">*Not Localized* Object Description</LANG>
    <LANG ID="es-ES">*Not Localized* Object Description</LANG>
    <LANG ID="ja-JP">えっ、こんなわしからモノをせびるのか？\n何というやつだ！</LANG>
    <LANG ID="ko-KR">*Not Localized* Object Description</LANG>
    <LANG ID="en-SG">*Not Localized* Object Description</LANG>
    <LANG ID="zh-HK">*Not Localized* Object Description</LANG>
    <LANG ID="zh-TW">*Not Localized* Object Description</LANG>
    <LANG ID="en-US">*Not Localized* Object Description</LANG>
  </PHRASE>
  <PHRASE>
    <LANG ID="REF">APR_001_25</LANG>
    <LANG ID="en-GB">*Not Localized* Object Description</LANG>
    <LANG ID="fr-FR">*Not Localized* Object Description</LANG>
    <LANG ID="de-DE">*Not Localized* Object Description</LANG>
    <LANG ID="it-IT">*Not Localized* Object Description</LANG>
    <LANG ID="es-ES">*Not Localized* Object Description</LANG>
    <LANG ID="ja-JP">わかったから\nとにかくキースにわしの無念を伝えてくれ</LANG>
    <LANG ID="ko-KR">*Not Localized* Object Description</LANG>
    <LANG ID="en-SG">*Not Localized* Object Description</LANG>
    <LANG ID="zh-HK">*Not Localized* Object Description</LANG>
    <LANG ID="zh-TW">*Not Localized* Object Description</LANG>
    <LANG ID="en-US">*Not Localized* Object Description</LANG>
  </PHRASE>
  <PHRASE>
    <LANG ID="REF">APR_001_26</LANG>
    <LANG ID="en-GB">*Not Localized* Object Description</LANG>
    <LANG ID="fr-FR">*Not Localized* Object Description</LANG>
    <LANG ID="de-DE">*Not Localized* Object Description</LANG>
    <LANG ID="it-IT">*Not Localized* Object Description</LANG>
    <LANG ID="es-ES">*Not Localized* Object Description</LANG>
    <LANG ID="ja-JP">うるさいこのガイコツ野郎め！</LANG>
    <LANG ID="ko-KR">*Not Localized* Object Description</LANG>
    <LANG ID="en-SG">*Not Localized* Object Description</LANG>
    <LANG ID="zh-HK">*Not Localized* Object Description</LANG>
    <LANG ID="zh-TW">*Not Localized* Object Description</LANG>
    <LANG ID="en-US">*Not Localized* Object Description</LANG>
  </PHRASE>
  <PHRASE>
    <LANG ID="REF">APR_001_27</LANG>
    <LANG ID="en-GB">*Not Localized* Object Description</LANG>
    <LANG ID="fr-FR">*Not Localized* Object Description</LANG>
    <LANG ID="de-DE">*Not Localized* Object Description</LANG>
    <LANG ID="it-IT">*Not Localized* Object Description</LANG>
    <LANG ID="es-ES">*Not Localized* Object Description</LANG>
    <LANG ID="ja-JP">なんじゃと！\n誰も好き好んでこんな姿になったのではないぞい</LANG>
    <LANG ID="ko-KR">*Not Localized* Object Description</LANG>
    <LANG ID="en-SG">*Not Localized* Object Description</LANG>
    <LANG ID="zh-HK">*Not Localized* Object Description</LANG>
    <LANG ID="zh-TW">*Not Localized* Object Description</LANG>
    <LANG ID="en-US">*Not Localized* Object Description</LANG>
  </PHRASE>
  <PHRASE>
    <LANG ID="REF">APR_001_28</LANG>
    <LANG ID="en-GB">*Not Localized* Object Description</LANG>
    <LANG ID="fr-FR">*Not Localized* Object Description</LANG>
    <LANG ID="de-DE">*Not Localized* Object Description</LANG>
    <LANG ID="it-IT">*Not Localized* Object Description</LANG>
    <LANG ID="es-ES">*Not Localized* Object Description</LANG>
    <LANG ID="ja-JP">この無礼者め！とにかくキースにわしの無念を伝えてくれ</LANG>
    <LANG ID="ko-KR">*Not Localized* Object Description</LANG>
    <LANG ID="en-SG">*Not Localized* Object Description</LANG>
    <LANG ID="zh-HK">*Not Localized* Object Description</LANG>
    <LANG ID="zh-TW">*Not Localized* Object Description</LANG>
    <LANG ID="en-US">*Not Localized* Object Description</LANG>
  </PHRASE>
  <PHRASE>
    <LANG ID="REF">APR_002_1</LANG>
    <LANG ID="en-GB">*Not Localized* Object Description</LANG>
    <LANG ID="fr-FR">*Not Localized* Object Description</LANG>
    <LANG ID="de-DE">*Not Localized* Object Description</LANG>
    <LANG ID="it-IT">*Not Localized* Object Description</LANG>
    <LANG ID="es-ES">*Not Localized* Object Description</LANG>
    <LANG ID="ja-JP">わしをだましおって…　本当に無念じゃ…</LANG>
    <LANG ID="ko-KR">*Not Localized* Object Description</LANG>
    <LANG ID="en-SG">*Not Localized* Object Description</LANG>
    <LANG ID="zh-HK">*Not Localized* Object Description</LANG>
    <LANG ID="zh-TW">*Not Localized* Object Description</LANG>
    <LANG ID="en-US">*Not Localized* Object Description</LANG>
  </PHRASE>
  <PHRASE>
    <LANG ID="REF">APR_002_2</LANG>
    <LANG ID="en-GB">*Not Localized* Object Description</LANG>
    <LANG ID="fr-FR">*Not Localized* Object Description</LANG>
    <LANG ID="de-DE">*Not Localized* Object Description</LANG>
    <LANG ID="it-IT">*Not Localized* Object Description</LANG>
    <LANG ID="es-ES">*Not Localized* Object Description</LANG>
    <LANG ID="ja-JP">キースはまだ船にいるはずだ\nわしの無念をヤツに伝えてくれ</LANG>
    <LANG ID="ko-KR">*Not Localized* Object Description</LANG>
    <LANG ID="en-SG">*Not Localized* Object Description</LANG>
    <LANG ID="zh-HK">*Not Localized* Object Description</LANG>
    <LANG ID="zh-TW">*Not Localized* Object Description</LANG>
    <LANG ID="en-US">*Not Localized* Object Description</LANG>
  </PHRASE>
  <PHRASE>
    <LANG ID="REF">APR_003_1</LANG>
    <LANG ID="en-GB">*Not Localized* Object Description</LANG>
    <LANG ID="fr-FR">*Not Localized* Object Description</LANG>
    <LANG ID="de-DE">*Not Localized* Object Description</LANG>
    <LANG ID="it-IT">*Not Localized* Object Description</LANG>
    <LANG ID="es-ES">*Not Localized* Object Description</LANG>
    <LANG ID="ja-JP">どうだった？　わしの無念を聞いて\nキースは何と言っていたのだ？</LANG>
    <LANG ID="ko-KR">*Not Localized* Object Description</LANG>
    <LANG ID="en-SG">*Not Localized* Object Description</LANG>
    <LANG ID="zh-HK">*Not Localized* Object Description</LANG>
    <LANG ID="zh-TW">*Not Localized* Object Description</LANG>
    <LANG ID="en-US">*Not Localized* Object Description</LANG>
  </PHRASE>
  <PHRASE>
    <LANG ID="REF">APR_003_1_A</LANG>
    <LANG ID="en-GB">*Not Localized* Object Description</LANG>
    <LANG ID="fr-FR">*Not Localized* Object Description</LANG>
    <LANG ID="de-DE">*Not Localized* Object Description</LANG>
    <LANG ID="it-IT">*Not Localized* Object Description</LANG>
    <LANG ID="es-ES">*Not Localized* Object Description</LANG>
    <LANG ID="ja-JP">どうも船長の誤解のようです　と事情を説明する</LANG>
    <LANG ID="ko-KR">*Not Localized* Object Description</LANG>
    <LANG ID="en-SG">*Not Localized* Object Description</LANG>
    <LANG ID="zh-HK">*Not Localized* Object Description</LANG>
    <LANG ID="zh-TW">*Not Localized* Object Description</LANG>
    <LANG ID="en-US">*Not Localized* Object Description</LANG>
  </PHRASE>
  <PHRASE>
    <LANG ID="REF">APR_003_1_B</LANG>
    <LANG ID="en-GB">*Not Localized* Object Description</LANG>
    <LANG ID="fr-FR">*Not Localized* Object Description</LANG>
    <LANG ID="de-DE">*Not Localized* Object Description</LANG>
    <LANG ID="it-IT">*Not Localized* Object Description</LANG>
    <LANG ID="es-ES">*Not Localized* Object Description</LANG>
    <LANG ID="ja-JP">騙されるヤツが悪いと言っていた　とウソを伝える</LANG>
    <LANG ID="ko-KR">*Not Localized* Object Description</LANG>
    <LANG ID="en-SG">*Not Localized* Object Description</LANG>
    <LANG ID="zh-HK">*Not Localized* Object Description</LANG>
    <LANG ID="zh-TW">*Not Localized* Object Description</LANG>
    <LANG ID="en-US">*Not Localized* Object Description</LANG>
  </PHRASE>
  <PHRASE>
    <LANG ID="REF">APR_003_2</LANG>
    <LANG ID="en-GB">*Not Localized* Object Description</LANG>
    <LANG ID="fr-FR">*Not Localized* Object Description</LANG>
    <LANG ID="de-DE">*Not Localized* Object Description</LANG>
    <LANG ID="it-IT">*Not Localized* Object Description</LANG>
    <LANG ID="es-ES">*Not Localized* Object Description</LANG>
    <LANG ID="ja-JP">どうも船長の誤解のようです\n彼は、この入り江に海竜がいることを\n知らなかったようです。</LANG>
    <LANG ID="ko-KR">*Not Localized* Object Description</LANG>
    <LANG ID="en-SG">*Not Localized* Object Description</LANG>
    <LANG ID="zh-HK">*Not Localized* Object Description</LANG>
    <LANG ID="zh-TW">*Not Localized* Object Description</LANG>
    <LANG ID="en-US">*Not Localized* Object Description</LANG>
  </PHRASE>
  <PHRASE>
    <LANG ID="REF">APR_003_3</LANG>
    <LANG ID="en-GB">*Not Localized* Object Description</LANG>
    <LANG ID="fr-FR">*Not Localized* Object Description</LANG>
    <LANG ID="de-DE">*Not Localized* Object Description</LANG>
    <LANG ID="it-IT">*Not Localized* Object Description</LANG>
    <LANG ID="es-ES">*Not Localized* Object Description</LANG>
    <LANG ID="ja-JP">わしはだまされんぞ！</LANG>
    <LANG ID="ko-KR">*Not Localized* Object Description</LANG>
    <LANG ID="en-SG">*Not Localized* Object Description</LANG>
    <LANG ID="zh-HK">*Not Localized* Object Description</LANG>
    <LANG ID="zh-TW">*Not Localized* Object Description</LANG>
    <LANG ID="en-US">*Not Localized* Object Description</LANG>
  </PHRASE>
  <PHRASE>
    <LANG ID="REF">APR_003_4</LANG>
    <LANG ID="en-GB">*Not Localized* Object Description</LANG>
    <LANG ID="fr-FR">*Not Localized* Object Description</LANG>
    <LANG ID="de-DE">*Not Localized* Object Description</LANG>
    <LANG ID="it-IT">*Not Localized* Object Description</LANG>
    <LANG ID="es-ES">*Not Localized* Object Description</LANG>
    <LANG ID="ja-JP">それに彼は、船長に謝罪していましたよ</LANG>
    <LANG ID="ko-KR">*Not Localized* Object Description</LANG>
    <LANG ID="en-SG">*Not Localized* Object Description</LANG>
    <LANG ID="zh-HK">*Not Localized* Object Description</LANG>
    <LANG ID="zh-TW">*Not Localized* Object Description</LANG>
    <LANG ID="en-US">*Not Localized* Object Description</LANG>
  </PHRASE>
  <PHRASE>
    <LANG ID="REF">APR_003_5</LANG>
    <LANG ID="en-GB">*Not Localized* Object Description</LANG>
    <LANG ID="fr-FR">*Not Localized* Object Description</LANG>
    <LANG ID="de-DE">*Not Localized* Object Description</LANG>
    <LANG ID="it-IT">*Not Localized* Object Description</LANG>
    <LANG ID="es-ES">*Not Localized* Object Description</LANG>
    <LANG ID="ja-JP">何、キースがわしに謝っていたと…\nわしは、本当に勘違いしていたのかも知れん…</LANG>
    <LANG ID="ko-KR">*Not Localized* Object Description</LANG>
    <LANG ID="en-SG">*Not Localized* Object Description</LANG>
    <LANG ID="zh-HK">*Not Localized* Object Description</LANG>
    <LANG ID="zh-TW">*Not Localized* Object Description</LANG>
    <LANG ID="en-US">*Not Localized* Object Description</LANG>
  </PHRASE>
  <PHRASE>
    <LANG ID="REF">APR_003_6</LANG>
    <LANG ID="en-GB">*Not Localized* Object Description</LANG>
    <LANG ID="fr-FR">*Not Localized* Object Description</LANG>
    <LANG ID="de-DE">*Not Localized* Object Description</LANG>
    <LANG ID="it-IT">*Not Localized* Object Description</LANG>
    <LANG ID="es-ES">*Not Localized* Object Description</LANG>
    <LANG ID="ja-JP">うむ……………キース…</LANG>
    <LANG ID="ko-KR">*Not Localized* Object Description</LANG>
    <LANG ID="en-SG">*Not Localized* Object Description</LANG>
    <LANG ID="zh-HK">*Not Localized* Object Description</LANG>
    <LANG ID="zh-TW">*Not Localized* Object Description</LANG>
    <LANG ID="en-US">*Not Localized* Object Description</LANG>
  </PHRASE>
  <PHRASE>
    <LANG ID="REF">APR_003_7</LANG>
    <LANG ID="en-GB">*Not Localized* Object Description</LANG>
    <LANG ID="fr-FR">*Not Localized* Object Description</LANG>
    <LANG ID="de-DE">*Not Localized* Object Description</LANG>
    <LANG ID="it-IT">*Not Localized* Object Description</LANG>
    <LANG ID="es-ES">*Not Localized* Object Description</LANG>
    <LANG ID="ja-JP">確かに、キースは船乗りの中でも\nもっとも忠義を尽くすやつだったな…</LANG>
    <LANG ID="ko-KR">*Not Localized* Object Description</LANG>
    <LANG ID="en-SG">*Not Localized* Object Description</LANG>
    <LANG ID="zh-HK">*Not Localized* Object Description</LANG>
    <LANG ID="zh-TW">*Not Localized* Object Description</LANG>
    <LANG ID="en-US">*Not Localized* Object Description</LANG>
  </PHRASE>
  <PHRASE>
    <LANG ID="REF">APR_003_8</LANG>
    <LANG ID="en-GB">*Not Localized* Object Description</LANG>
    <LANG ID="fr-FR">*Not Localized* Object Description</LANG>
    <LANG ID="de-DE">*Not Localized* Object Description</LANG>
    <LANG ID="it-IT">*Not Localized* Object Description</LANG>
    <LANG ID="es-ES">*Not Localized* Object Description</LANG>
    <LANG ID="ja-JP">わしは勘違いしていたのか…</LANG>
    <LANG ID="ko-KR">*Not Localized* Object Description</LANG>
    <LANG ID="en-SG">*Not Localized* Object Description</LANG>
    <LANG ID="zh-HK">*Not Localized* Object Description</LANG>
    <LANG ID="zh-TW">*Not Localized* Object Description</LANG>
    <LANG ID="en-US">*Not Localized* Object Description</LANG>
  </PHRASE>
  <PHRASE>
    <LANG ID="REF">APR_003_9</LANG>
    <LANG ID="en-GB">*Not Localized* Object Description</LANG>
    <LANG ID="fr-FR">*Not Localized* Object Description</LANG>
    <LANG ID="de-DE">*Not Localized* Object Description</LANG>
    <LANG ID="it-IT">*Not Localized* Object Description</LANG>
    <LANG ID="es-ES">*Not Localized* Object Description</LANG>
    <LANG ID="ja-JP">お前さん、キースに謝っておいてくれ\n疑って悪かったと…</LANG>
    <LANG ID="ko-KR">*Not Localized* Object Description</LANG>
    <LANG ID="en-SG">*Not Localized* Object Description</LANG>
    <LANG ID="zh-HK">*Not Localized* Object Description</LANG>
    <LANG ID="zh-TW">*Not Localized* Object Description</LANG>
    <LANG ID="en-US">*Not Localized* Object Description</LANG>
  </PHRASE>
  <PHRASE>
    <LANG ID="REF">APR_003_10</LANG>
    <LANG ID="en-GB">*Not Localized* Object Description</LANG>
    <LANG ID="fr-FR">*Not Localized* Object Description</LANG>
    <LANG ID="de-DE">*Not Localized* Object Description</LANG>
    <LANG ID="it-IT">*Not Localized* Object Description</LANG>
    <LANG ID="es-ES">*Not Localized* Object Description</LANG>
    <LANG ID="ja-JP">わしの無念は晴れた\nそろそろ成仏するかな…</LANG>
    <LANG ID="ko-KR">*Not Localized* Object Description</LANG>
    <LANG ID="en-SG">*Not Localized* Object Description</LANG>
    <LANG ID="zh-HK">*Not Localized* Object Description</LANG>
    <LANG ID="zh-TW">*Not Localized* Object Description</LANG>
    <LANG ID="en-US">*Not Localized* Object Description</LANG>
  </PHRASE>
  <PHRASE>
    <LANG ID="REF">APR_003_21</LANG>
    <LANG ID="en-GB">*Not Localized* Object Description</LANG>
    <LANG ID="fr-FR">*Not Localized* Object Description</LANG>
    <LANG ID="de-DE">*Not Localized* Object Description</LANG>
    <LANG ID="it-IT">*Not Localized* Object Description</LANG>
    <LANG ID="es-ES">*Not Localized* Object Description</LANG>
    <LANG ID="ja-JP">騙されるヤツが悪いんだと言っていたよ</LANG>
    <LANG ID="ko-KR">*Not Localized* Object Description</LANG>
    <LANG ID="en-SG">*Not Localized* Object Description</LANG>
    <LANG ID="zh-HK">*Not Localized* Object Description</LANG>
    <LANG ID="zh-TW">*Not Localized* Object Description</LANG>
    <LANG ID="en-US">*Not Localized* Object Description</LANG>
  </PHRASE>
  <PHRASE>
    <LANG ID="REF">APR_003_22</LANG>
    <LANG ID="en-GB">*Not Localized* Object Description</LANG>
    <LANG ID="fr-FR">*Not Localized* Object Description</LANG>
    <LANG ID="de-DE">*Not Localized* Object Description</LANG>
    <LANG ID="it-IT">*Not Localized* Object Description</LANG>
    <LANG ID="es-ES">*Not Localized* Object Description</LANG>
    <LANG ID="ja-JP">何じゃと！\nけしからん！　まったくけしからん話じゃ</LANG>
    <LANG ID="ko-KR">*Not Localized* Object Description</LANG>
    <LANG ID="en-SG">*Not Localized* Object Description</LANG>
    <LANG ID="zh-HK">*Not Localized* Object Description</LANG>
    <LANG ID="zh-TW">*Not Localized* Object Description</LANG>
    <LANG ID="en-US">*Not Localized* Object Description</LANG>
  </PHRASE>
  <PHRASE>
    <LANG ID="REF">APR_003_23</LANG>
    <LANG ID="en-GB">*Not Localized* Object Description</LANG>
    <LANG ID="fr-FR">*Not Localized* Object Description</LANG>
    <LANG ID="de-DE">*Not Localized* Object Description</LANG>
    <LANG ID="it-IT">*Not Localized* Object Description</LANG>
    <LANG ID="es-ES">*Not Localized* Object Description</LANG>
    <LANG ID="ja-JP">あれほど面倒見てやったのに…\n無念を通り越して力が抜けていく…</LANG>
    <LANG ID="ko-KR">*Not Localized* Object Description</LANG>
    <LANG ID="en-SG">*Not Localized* Object Description</LANG>
    <LANG ID="zh-HK">*Not Localized* Object Description</LANG>
    <LANG ID="zh-TW">*Not Localized* Object Description</LANG>
    <LANG ID="en-US">*Not Localized* Object Description</LANG>
  </PHRASE>
  <PHRASE>
    <LANG ID="REF">APR_003_24</LANG>
    <LANG ID="en-GB">*Not Localized* Object Description</LANG>
    <LANG ID="fr-FR">*Not Localized* Object Description</LANG>
    <LANG ID="de-DE">*Not Localized* Object Description</LANG>
    <LANG ID="it-IT">*Not Localized* Object Description</LANG>
    <LANG ID="es-ES">*Not Localized* Object Description</LANG>
    <LANG ID="ja-JP">………うっ！　ダメだ\n脱力したら、成仏してしまいそうじゃ…く…</LANG>
    <LANG ID="ko-KR">*Not Localized* Object Description</LANG>
    <LANG ID="en-SG">*Not Localized* Object Description</LANG>
    <LANG ID="zh-HK">*Not Localized* Object Description</LANG>
    <LANG ID="zh-TW">*Not Localized* Object Description</LANG>
    <LANG ID="en-US">*Not Localized* Object Description</LANG>
  </PHRASE>
  <PHRASE>
    <LANG ID="REF">APR_003_25</LANG>
    <LANG ID="en-GB">*Not Localized* Object Description</LANG>
    <LANG ID="fr-FR">*Not Localized* Object Description</LANG>
    <LANG ID="de-DE">*Not Localized* Object Description</LANG>
    <LANG ID="it-IT">*Not Localized* Object Description</LANG>
    <LANG ID="es-ES">*Not Localized* Object Description</LANG>
    <LANG ID="ja-JP">変な結末で申し訳ないが\nわしはここまでのようじゃ</LANG>
    <LANG ID="ko-KR">*Not Localized* Object Description</LANG>
    <LANG ID="en-SG">*Not Localized* Object Description</LANG>
    <LANG ID="zh-HK">*Not Localized* Object Description</LANG>
    <LANG ID="zh-TW">*Not Localized* Object Description</LANG>
    <LANG ID="en-US">*Not Localized* Object Description</LANG>
  </PHRASE>
  <PHRASE>
    <LANG ID="REF">APR_003_26</LANG>
    <LANG ID="en-GB">*Not Localized* Object Description</LANG>
    <LANG ID="fr-FR">*Not Localized* Object Description</LANG>
    <LANG ID="de-DE">*Not Localized* Object Description</LANG>
    <LANG ID="it-IT">*Not Localized* Object Description</LANG>
    <LANG ID="es-ES">*Not Localized* Object Description</LANG>
    <LANG ID="ja-JP">だが、長年信用してきたキースの本性が\nわかっただけでもよかった</LANG>
    <LANG ID="ko-KR">*Not Localized* Object Description</LANG>
    <LANG ID="en-SG">*Not Localized* Object Description</LANG>
    <LANG ID="zh-HK">*Not Localized* Object Description</LANG>
    <LANG ID="zh-TW">*Not Localized* Object Description</LANG>
    <LANG ID="en-US">*Not Localized* Object Description</LANG>
  </PHRASE>
  <PHRASE>
    <LANG ID="REF">APR_003_27</LANG>
    <LANG ID="en-GB">*Not Localized* Object Description</LANG>
    <LANG ID="fr-FR">*Not Localized* Object Description</LANG>
    <LANG ID="de-DE">*Not Localized* Object Description</LANG>
    <LANG ID="it-IT">*Not Localized* Object Description</LANG>
    <LANG ID="es-ES">*Not Localized* Object Description</LANG>
    <LANG ID="ja-JP">お前さんには感謝しとるぞ</LANG>
    <LANG ID="ko-KR">*Not Localized* Object Description</LANG>
    <LANG ID="en-SG">*Not Localized* Object Description</LANG>
    <LANG ID="zh-HK">*Not Localized* Object Description</LANG>
    <LANG ID="zh-TW">*Not Localized* Object Description</LANG>
    <LANG ID="en-US">*Not Localized* Object Description</LANG>
  </PHRASE>
  <PHRASE>
    <LANG ID="REF">APR_003_31</LANG>
    <LANG ID="en-GB">*Not Localized* Object Description</LANG>
    <LANG ID="fr-FR">*Not Localized* Object Description</LANG>
    <LANG ID="de-DE">*Not Localized* Object Description</LANG>
    <LANG ID="it-IT">*Not Localized* Object Description</LANG>
    <LANG ID="es-ES">*Not Localized* Object Description</LANG>
    <LANG ID="ja-JP">お前さんには、これを渡しておこう</LANG>
    <LANG ID="ko-KR">*Not Localized* Object Description</LANG>
    <LANG ID="en-SG">*Not Localized* Object Description</LANG>
    <LANG ID="zh-HK">*Not Localized* Object Description</LANG>
    <LANG ID="zh-TW">*Not Localized* Object Description</LANG>
    <LANG ID="en-US">*Not Localized* Object Description</LANG>
  </PHRASE>
  <PHRASE>
    <LANG ID="REF">APR_003_32</LANG>
    <LANG ID="en-GB">*Not Localized* Object Description</LANG>
    <LANG ID="fr-FR">*Not Localized* Object Description</LANG>
    <LANG ID="de-DE">*Not Localized* Object Description</LANG>
    <LANG ID="it-IT">*Not Localized* Object Description</LANG>
    <LANG ID="es-ES">*Not Localized* Object Description</LANG>
    <LANG ID="ja-JP">それで、砂浜の入り口付近にある\n行き先案内を調べれば、「ヤミィの森」に行けるはずだ…</LANG>
    <LANG ID="ko-KR">*Not Localized* Object Description</LANG>
    <LANG ID="en-SG">*Not Localized* Object Description</LANG>
    <LANG ID="zh-HK">*Not Localized* Object Description</LANG>
    <LANG ID="zh-TW">*Not Localized* Object Description</LANG>
    <LANG ID="en-US">*Not Localized* Object Description</LANG>
  </PHRASE>
  <PHRASE>
    <LANG ID="REF">APR_003_33</LANG>
    <LANG ID="en-GB">*Not Localized* Object Description</LANG>
    <LANG ID="fr-FR">*Not Localized* Object Description</LANG>
    <LANG ID="de-DE">*Not Localized* Object Description</LANG>
    <LANG ID="it-IT">*Not Localized* Object Description</LANG>
    <LANG ID="es-ES">*Not Localized* Object Description</LANG>
    <LANG ID="ja-JP">それでは、さらばだ…</LANG>
    <LANG ID="ko-KR">*Not Localized* Object Description</LANG>
    <LANG ID="en-SG">*Not Localized* Object Description</LANG>
    <LANG ID="zh-HK">*Not Localized* Object Description</LANG>
    <LANG ID="zh-TW">*Not Localized* Object Description</LANG>
    <LANG ID="en-US">*Not Localized* Object Description</LANG>
  </PHRASE>
  <PHRASE>
    <LANG ID="REF">APR_003_34</LANG>
    <LANG ID="en-GB">*Not Localized* Object Description</LANG>
    <LANG ID="fr-FR">*Not Localized* Object Description</LANG>
    <LANG ID="de-DE">*Not Localized* Object Description</LANG>
    <LANG ID="it-IT">*Not Localized* Object Description</LANG>
    <LANG ID="es-ES">*Not Localized* Object Description</LANG>
    <LANG ID="ja-JP">そして、ガイコツ船長は海の中に溶け込むように\n消えていった…</LANG>
    <LANG ID="ko-KR">*Not Localized* Object Description</LANG>
    <LANG ID="en-SG">*Not Localized* Object Description</LANG>
    <LANG ID="zh-HK">*Not Localized* Object Description</LANG>
    <LANG ID="zh-TW">*Not Localized* Object Description</LANG>
    <LANG ID="en-US">*Not Localized* Object Description</LANG>
  </PHRASE>
  <PHRASE>
    <LANG ID="REF">APR_004_1</LANG>
    <LANG ID="en-GB">*Not Localized* Object Description</LANG>
    <LANG ID="fr-FR">*Not Localized* Object Description</LANG>
    <LANG ID="de-DE">*Not Localized* Object Description</LANG>
    <LANG ID="it-IT">*Not Localized* Object Description</LANG>
    <LANG ID="es-ES">*Not Localized* Object Description</LANG>
    <LANG ID="ja-JP">船長の姿はない…</LANG>
    <LANG ID="ko-KR">*Not Localized* Object Description</LANG>
    <LANG ID="en-SG">*Not Localized* Object Description</LANG>
    <LANG ID="zh-HK">*Not Localized* Object Description</LANG>
    <LANG ID="zh-TW">*Not Localized* Object Description</LANG>
    <LANG ID="en-US">*Not Localized* Object Description</LANG>
  </PHRASE>
</LOCALISATION>