<?xml version="1.0" encoding="utf-8"?>
<LOCALISATION xmlns:xsi="http://www.w3.org/2001/XMLSchema-instance" xmlns:xs="http://www.w3.org/2001/XMLSchema" default_language="en-GB" xmlns="http://home.scedev.net/schema/object">
  <PHRASE>
    <LANG ID="REF">kName</LANG>
    <LANG ID="en-GB">Tombstone Chair</LANG>
    <LANG ID="fr-FR">Chaise pierre tombale</LANG>
    <LANG ID="de-DE">Grabsteinstuhl</LANG>
    <LANG ID="it-IT">Lapide-sedia</LANG>
    <LANG ID="es-ES">Silla lápida</LANG>
    <LANG ID="ja-JP">トゥームストーンチェア</LANG>
    <LANG ID="ko-KR">묘비 의자</LANG>
    <LANG ID="en-SG">Tombstone Chair</LANG>
    <LANG ID="zh-HK">墓碑椅</LANG>
    <LANG ID="zh-TW">墓碑椅</LANG>
    <LANG ID="en-US">Tombstone Chair</LANG>
  </PHRASE>
  <PHRASE>
    <LANG ID="REF">kDesc</LANG>
    <LANG ID="en-GB">Be the king of your graveyard with this scary Tombstone Chair! [#Legal]</LANG>
    <LANG ID="fr-FR">Soyez le roi du cimetière avec cette effrayante chaise pierre tombale ! [#Legal]</LANG>
    <LANG ID="de-DE">Throne auf diesem gruseligen Grabsteinstuhl wie der König deines Friedhofs! [#Legal]</LANG>
    <LANG ID="it-IT">Domina il tuo cimitero con questa spaventosa lapide-sedia! [#Legal]</LANG>
    <LANG ID="es-ES">¡Si usas esta lápida a modo de silla serás el rey del cementerio! [#Legal]</LANG>
    <LANG ID="ja-JP">この怖～いトゥームストーンチェアで墓地の王様になってみましょう！[#Legal]</LANG>
    <LANG ID="ko-KR">괴기스러운 묘비 의자에 앉아 무덤의 주인이 되어 보십시오. [#Legal]</LANG>
    <LANG ID="en-SG">Be the king of your graveyard with this scary Tombstone Chair! [#Legal]</LANG>
    <LANG ID="zh-HK">用這墓碑椅來當您自己的墓地之王！[#Legal]</LANG>
    <LANG ID="zh-TW">用這墓碑椅來當您自己的墓地之王！[#Legal]</LANG>
    <LANG ID="en-US">Be the king of your graveyard with this scary Tombstone Chair! [#Legal]</LANG>
  </PHRASE>
</LOCALISATION>