<?xml version="1.0" encoding="utf-8"?>
<LOCALISATION xmlns:xsi="http://www.w3.org/2001/XMLSchema-instance" xmlns:xs="http://www.w3.org/2001/XMLSchema" default_language="en-GB" xmlns="http://home.scedev.net/schema/object">
  <PHRASE>
    <LANG ID="REF">kName</LANG>
    <LANG ID="en-GB">Damask Print Jacket - White (Men)</LANG>
    <LANG ID="fr-FR">Blouson damassé imprimé - Blanc (homme)</LANG>
    <LANG ID="de-DE">Bedruckte Jacke aus Damast - Weiß (Herren)</LANG>
    <LANG ID="it-IT">Giacca damascata - Bianco (Uomo)</LANG>
    <LANG ID="es-ES">Chaqueta damasco con estampado - Blanco (Hombre)</LANG>
  </PHRASE>
  <PHRASE>
    <LANG ID="REF">kDesc</LANG>
    <LANG ID="en-GB">A damask patterend winter jacket with a purple under shirt. [#Legal]</LANG>
    <LANG ID="fr-FR">Un blouson d'hiver à motif damassé avec un tricot violet. [#Legal]</LANG>
    <LANG ID="de-DE">Gemusterte Winterjacke aus Damast mit purpurrotem Unterhemd. [#Legal]</LANG>
    <LANG ID="it-IT">Giacca invernale damascata con maglietta viola. [#Legal]</LANG>
    <LANG ID="es-ES">Una chaqueta de damasco para invierno y con dibujo, con camisa púrpura por debajo. [#Legal]</LANG>
    <LANG ID="Type">Batch 14 [#Legal]</LANG>
  </PHRASE>
</LOCALISATION>