<?xml version="1.0" encoding="utf-8"?>
<LOCALISATION xmlns:xsi="http://www.w3.org/2001/XMLSchema-instance" xmlns:xs="http://www.w3.org/2001/XMLSchema" default_language="en-GB" xmlns="http://home.scedev.net/schema/object">
  <PHRASE>
    <LANG ID="REF">kName</LANG>
    <LANG ID="en-GB">House Raleigh Grand Vase</LANG>
    <LANG ID="fr-FR">Maison Raleigh grande vase</LANG>
    <LANG ID="de-DE">Haus Raleigh große Vase</LANG>
    <LANG ID="it-IT">Casa Raleigh grande vaso</LANG>
    <LANG ID="es-ES">Casa Raleigh de gran jarrón</LANG>
    <LANG ID="ja-JP">デュモン家の大花瓶</LANG>
    <LANG ID="ko-KR">뒤몽 집 큰 꽃병</LANG>
    <LANG ID="en-SG">House Raleigh Grand Vase</LANG>
    <LANG ID="zh-HK">杜蒙房子大花瓶</LANG>
    <LANG ID="zh-TW">杜蒙房子大花瓶</LANG>
    <LANG ID="en-US">House Raleigh Grand Vase</LANG>
  </PHRASE>
  <PHRASE>
    <LANG ID="REF">kDesc</LANG>
    <LANG ID="en-GB">A magnificent vase made of marble and precious metals  styled after the Raleigh crest.[#Legal]</LANG>
    <LANG ID="fr-FR">Un magnifique vase en marbre et les métaux précieux style après la crête Raleigh.[#Legal]</LANG>
    <LANG ID="de-DE">Eine schöne Marmorvase Stil und Edelmetallen nach dem Höhepunkt Raleigh.[#Legal]</LANG>
    <LANG ID="it-IT">Un bellissimo vaso di marmo in stile e metalli preziosi dopo il picco di Raleigh.[#Legal]</LANG>
    <LANG ID="es-ES">Un jarrón de mármol de estilo y los metales preciosos después de que el pico de Raleigh.[#Legal]</LANG>
    <LANG ID="ja-JP">大理石とローリー紋章にちなん貴金属で作られた壮大な花瓶。[#Legal]</LANG>
    <LANG ID="ko-KR">대리석과 귀금속으로 만들어진 아름다운 화병은 롤리 문장 후 스타일.[#Legal]</LANG>
    <LANG ID="en-SG">A magnificent vase made of marble and precious metals  styled after the Raleigh crest.[#Legal]</LANG>
    <LANG ID="zh-HK">雄伟的大理石和贵重金属制成的花瓶样式后，罗利的波峰。[#Legal]</LANG>
    <LANG ID="zh-TW">雄伟的大理石和贵重金属制成的花瓶样式后，罗利的波峰。[#Legal]</LANG>
    <LANG ID="en-US">A magnificent vase made of marble and precious metals  styled after the Raleigh crest.[#Legal]</LANG>
  </PHRASE>
</LOCALISATION>