<?xml version="1.0" encoding="utf-8"?>
<LOCALISATION xmlns:xsi="http://www.w3.org/2001/XMLSchema-instance" xmlns:xs="http://www.w3.org/2001/XMLSchema" default_language="en-GB" xmlns="http://home.scedev.net/schema/object">
  <PHRASE>
    <LANG ID="REF">kName</LANG>
    <LANG ID="en-GB">Billabong - Release Bundle - Volume 28 (Women)</LANG>
    <LANG ID="fr-FR">Billabong - Lot de sortie - Volume 28 (Femme)</LANG>
    <LANG ID="de-DE">Billabong - Release Set - Volume 28 (Damen)</LANG>
    <LANG ID="it-IT">Billabong - Set di lancio - Volume 28 (Donna)</LANG>
    <LANG ID="es-ES">Billabong - Pack de lanzamiento - Volumen 28 (Mujer)</LANG>
  </PHRASE>
  <PHRASE>
    <LANG ID="REF">kDesc</LANG>
    <LANG ID="en-GB">Billabong - Release Bundle - Volume 28 (Women)\n
\n
This bundle contains:\n
(1) Billabong - Glass Petals Dress - Black (Women)\n
(2) Billabong - Before Me Crop Top - Peacoat (Women)\n
(3) Billabong - Clouds Above Crop Tank Top - Lemon Zest (Women)\n
(4) Billabong - Salty Daze Long Sleeve Spring Suit - Off Black Multi (Women)\n
(5) Billabong - Get Ziggy With It Skirt - Black (Women)\n
(6) Billabong - Lite Hearted Bazaar Denim Shorts - Blue Daze (Women)\n
(7) Billabong - Midday Freeing Hat - Ginger (Women)\n
(8) Billabong - Skip a Beat Rashguard - Black (Women) [#Legal]</LANG>
    <LANG ID="fr-FR">Billabong - Lot de sortie - Volume 28 (Femme)\n
\n
Ce lot contient :\n
(1) Billabong - Robe Glass Petals - Noir (Femme)\n
(2) Billabong - Top court Before Me - Bleu foncé (Femme)\n
(3) Billabong - Débardeur Clouds Above - Zest de citron (Femme)\n
(4) Billabong - Combi-short Salty Daze à manches longues - Gris-noir Multi (Femme)\n
(5) Billabong - Jupe Get Ziggy With It - Noir (Femme)\n
(6) Billabong - Shorts en jean Lite Hearted Bazaar - Bleu pervenche (Femme)\n
(7) Billabong - Chapeau Midday Freeing - Gingembre (Femme)\n
(8) Billabong - Top Skip a Beat - Noir (Femme) [#Legal]</LANG>
    <LANG ID="de-DE">Billabong - Release Set - Volume 28 (Damen)\n
\n
Dieses Paket enthält:\n
(1) Billabong - Glass Petals Kleid - Schwarz (Damen)\n
(2) Billabong - Before Me Bauchfreies Oberteil - Blaugrau (Damen)\n
(3) Billabong - Clouds Above Bauchfreies Tanktop - Limonengelb (Damen)\n
(4) Billabong - Salty Daze Langärmeliger Frühlingstaucheranzug - Dunkelgrau/Mehrfarbig (Damen)\n
(5) Billabong - Get Ziggy With It Rock - Schwarz (Damen)\n
(6) Billabong - Lite Hearted Bazaar Jeansshorts - Blau (Damen)\n
(7) Billabong - Midday Freeing Hut - Rotbraun (Damen)\n
(8) Billabong - Skip a Beat Rashguard - Black (Women) [#Legal]</LANG>
    <LANG ID="it-IT">Billabong - Set di lancio - Volume 28 (Donna)\n
\n
Il set comprende:\n
(1) Billabong - Glass Petals Vestito - Nero (Donna)\n
(2) Billabong - Before Me Top - Marinara (Donna)\n
(3) Billabong - Clouds Above Top a canottiera - Scorza di limone (Donna)\n
(4) Billabong - Salty Daze Costume da bagno a maniche lunghe - Nero e Multicolore (Donna)\n
(5) Billabong - Get Ziggy With It Gonna - Nero (Donna)\n
(6) Billabong - Lite Hearted Bazaar Pantaloncini in denim - Blu (Donna)\n
(7) Billabong - Midday Freeing Cappello - Zenzero (Donna)\n
(8) Billabong - Skip a Beat Rash guard - Nero (Donna) [#Legal]</LANG>
    <LANG ID="es-ES">Billabong - Pack de lanzamiento - Volumen 28 (Mujer)\n
\n
Este pack contiene:\n
(1) Billabong - Vestido Glass Petals - Negro (Mujer)\n
(2) Billabong - Camiseta corta Before Me - Marinero (Mujer)\n
(3) Billabong - Camiseta corta de manga sisa Clouds Above - Cáscara de limón (Mujer)\n
(4) Billabong - Shorty de manga larga Salty Daze - Negro apagado multicolor (Mujer)\n
(5) Billabong - Falda Get Ziggy With It - Negro (Mujer)\n
(6) Billabong - Short vaquero Lite Hearted Bazaar - Azul deslumbrante (Mujer)\n
(7) Billabong - Sombrero Midday Freeing - Rojo anaranjado (Mujer)\n
(8) Billabong - Top térmico Skip a Beat - Negro (Mujer) [#Legal]</LANG>
  </PHRASE>
</LOCALISATION>