<?xml version="1.0" encoding="utf-8"?>
<LOCALISATION xmlns:xsi="http://www.w3.org/2001/XMLSchema-instance" xmlns:xs="http://www.w3.org/2001/XMLSchema" default_language="ja-JP" xmlns="http://home.scedev.net/schema/object">
  <PHRASE>
    <LANG ID="REF">kName</LANG>
    <LANG ID="en-GB">Decorative Shelf</LANG>
    <LANG ID="fr-FR">Étagère décorative</LANG>
    <LANG ID="de-DE">Dekoratives Regal</LANG>
    <LANG ID="it-IT">Scaffale ornamentale</LANG>
    <LANG ID="es-ES">Estantería decorativa</LANG>
    <LANG ID="ja-JP">飾り棚</LANG>
    <LANG ID="ko-KR">Decorative Shelf</LANG>
    <LANG ID="en-SG">Decorative Shelf</LANG>
    <LANG ID="zh-HK">Decorative Shelf</LANG>
    <LANG ID="zh-TW">Decorative Shelf</LANG>
    <LANG ID="en-US">Decorative Shelf</LANG>
  </PHRASE>
  <PHRASE>
    <LANG ID="REF">kDesc</LANG>
    <LANG ID="en-GB">Decorative shelf with a nostalgic air. [#Legal]</LANG>
    <LANG ID="fr-FR">Étagère décorative à l'air nostalgique. [#Legal]</LANG>
    <LANG ID="de-DE">Dekoratives Regal mit nostalgischer Note. [#Legal]</LANG>
    <LANG ID="it-IT">Scaffale ornamentale di spirito nostalgico. [#Legal]</LANG>
    <LANG ID="es-ES">Estantería para decoración que despierta nostalgia. [#Legal]</LANG>
    <LANG ID="ja-JP">昔懐かしの雰囲気が漂う飾り棚。 [#Legal]</LANG>
    <LANG ID="ko-KR">Decorative shelf with a nostalgic air. [#Legal]</LANG>
    <LANG ID="en-SG">Decorative shelf with a nostalgic air. [#Legal]</LANG>
    <LANG ID="zh-HK">Decorative shelf with a nostalgic air. [#Legal]</LANG>
    <LANG ID="zh-TW">Decorative shelf with a nostalgic air. [#Legal]</LANG>
    <LANG ID="en-US">Decorative shelf with a nostalgic air. [#Legal]</LANG>
  </PHRASE>
</LOCALISATION>