<?xml version="1.0" encoding="utf-8"?>
<LOCALISATION xmlns:xsi="http://www.w3.org/2001/XMLSchema-instance" xmlns:xs="http://www.w3.org/2001/XMLSchema" default_language="en-US" xmlns="http://home.scedev.net/schema/object">
  <PHRASE>
    <LANG ID="REF">kName</LANG>
    <LANG ID="en-GB">Modern PC</LANG>
    <LANG ID="fr-FR">PC moderne</LANG>
    <LANG ID="de-DE">Moderner PC</LANG>
    <LANG ID="it-IT">PC moderno</LANG>
    <LANG ID="es-ES">PC moderno</LANG>
    <LANG ID="ja-JP">Modern PC</LANG>
    <LANG ID="ko-KR">Modern PC</LANG>
    <LANG ID="en-SG">Modern PC</LANG>
    <LANG ID="zh-HK">Modern PC</LANG>
    <LANG ID="zh-TW">Modern PC</LANG>
    <LANG ID="en-US">Modern PC</LANG>
  </PHRASE>
  <PHRASE>
    <LANG ID="REF">kDesc</LANG>
    <LANG ID="en-GB">Suitable for hardcore gaming, or just browsing the web. [#Legal]</LANG>
    <LANG ID="fr-FR">Idéal pour le hardcore gaming ou surfer sur le net. [#Legal]</LANG>
    <LANG ID="de-DE">Zum Hardcore-Gamen oder einfach nur im Internet surfen. [#Legal]</LANG>
    <LANG ID="it-IT">Adatto per videogiocatori accaniti o solo per navigare in rete. [#Legal]</LANG>
    <LANG ID="es-ES">Apto para largas horas de juego o sencillamente para navegar por Internet. [#Legal]</LANG>
    <LANG ID="ja-JP">Suitable for hardcore gaming, or just browsing the web. [#Legal]</LANG>
    <LANG ID="ko-KR">Suitable for hardcore gaming, or just browsing the web. [#Legal]</LANG>
    <LANG ID="en-SG">Suitable for hardcore gaming, or just browsing the web. [#Legal]</LANG>
    <LANG ID="zh-HK">Suitable for hardcore gaming, or just browsing the web. [#Legal]</LANG>
    <LANG ID="zh-TW">Suitable for hardcore gaming, or just browsing the web. [#Legal]</LANG>
    <LANG ID="en-US">Suitable for hardcore gaming, or just browsing the web. [#Legal]</LANG>
  </PHRASE>
</LOCALISATION>