<?xml version="1.0" encoding="utf-8"?>
<LOCALISATION xmlns:xsi="http://www.w3.org/2001/XMLSchema-instance" xmlns:xs="http://www.w3.org/2001/XMLSchema" default_language="en-GB" xmlns="http://home.scedev.net/schema/object">
  <PHRASE>
    <LANG ID="REF">kName</LANG>
    <LANG ID="en-GB">Download Vidzone now</LANG>
    <LANG ID="fr-FR">Télécharger Vidzone maintenant</LANG>
    <LANG ID="de-DE">VidZone jetzt herunterladen</LANG>
    <LANG ID="it-IT">Scarica Vidzone oggi stesso</LANG>
    <LANG ID="es-ES">Descarga VidZone ya</LANG>
  </PHRASE>
  <PHRASE>
    <LANG ID="REF">kDesc</LANG>
    <LANG ID="en-GB">VidZone™ - Free Music Video Application [#Legal]</LANG>
    <LANG ID="fr-FR">VidZone™ - l'application gratuite de clips musicaux [#Legal]</LANG>
    <LANG ID="de-DE">VidZone™ - die kostenlose Musikvideo-Anwendung [#Legal]</LANG>
    <LANG ID="it-IT">VidZone™ - l'applicazione di video musicali gratuita [#Legal]</LANG>
    <LANG ID="es-ES">VidZone™ -  la aplicación gratuita de vídeos musicales [#Legal]</LANG>
  </PHRASE>
</LOCALISATION>