<?xml version="1.0" encoding="utf-8"?>
<LOCALISATION xmlns:xsi="http://www.w3.org/2001/XMLSchema-instance" xmlns:xs="http://www.w3.org/2001/XMLSchema" default_language="en-GB" xmlns="http://home.scedev.net/schema/object">
  <PHRASE>
    <LANG ID="REF">kName</LANG>
    <LANG ID="en-GB">RockStar Companion</LANG>
    <LANG ID="fr-FR">Rockstar compagnon</LANG>
    <LANG ID="de-DE">Rockstar Begleiter</LANG>
    <LANG ID="it-IT">Rockstar compagno</LANG>
    <LANG ID="es-ES">Rockstar compañero</LANG>
    <LANG ID="ja-JP">*Not Localised* Home_Object_35</LANG>
    <LANG ID="ko-KR">RockStar Companion</LANG>
    <LANG ID="en-SG">RockStar Companion</LANG>
    <LANG ID="zh-HK">RockStar Companion</LANG>
    <LANG ID="zh-TW">RockStar Companion</LANG>
    <LANG ID="en-US">RockStar Companion</LANG>
  </PHRASE>
  <PHRASE>
    <LANG ID="REF">kDesc</LANG>
    <LANG ID="en-GB">You've collected so many Rockstars![#Legal]</LANG>
    <LANG ID="fr-FR">Vous avez recueilli tant de Rockstars!\n\nYou've collected so many Rockstars![#Legal]</LANG>
    <LANG ID="de-DE">Sie haben so viele Rockstars gesammelt!\n\nVous avez recueilli tant de Rockstars!\n\nYou've collected so many Rockstars![#Legal]</LANG>
    <LANG ID="it-IT">Hai raccolto Rockstars tanti!\n\nSie haben so viele Rockstars gesammelt!\n\nVous avez recueilli tant de Rockstars!\n\nYou've collected so many Rockstars![#Legal]</LANG>
    <LANG ID="es-ES">Ha reunido Rockstars tantas!\n\nHai raccolto Rockstars tanti!\n\nSie haben so viele Rockstars gesammelt!\n\nVous avez recueilli tant de Rockstars!\n\nYou've collected so many Rockstars![#Legal]</LANG>
    <LANG ID="ja-JP">*Not Localised* Home_Object_35 [#Legal]</LANG>
    <LANG ID="ko-KR">You've collected so many Rockstars![#Legal]</LANG>
    <LANG ID="en-SG">You've collected so many Rockstars![#Legal]</LANG>
    <LANG ID="zh-HK">You've collected so many Rockstars![#Legal]</LANG>
    <LANG ID="zh-TW">You've collected so many Rockstars![#Legal]</LANG>
    <LANG ID="en-US">You've collected so many Rockstars![#Legal]</LANG>
  </PHRASE>
</LOCALISATION>