<?xml version="1.0" encoding="utf-8"?>
<LOCALISATION xmlns:xsi="http://www.w3.org/2001/XMLSchema-instance" xmlns:xs="http://www.w3.org/2001/XMLSchema" default_language="en-US" xmlns="http://home.scedev.net/schema/object">
  <PHRASE>
    <LANG ID="REF">kName</LANG>
    <LANG ID="en-GB">Black Cable Knit Knee Socks</LANG>
    <LANG ID="fr-FR">Mi-bas en Tricot de Câble Noir</LANG>
    <LANG ID="de-DE">Schwarze,  Strickkniestrümpfe mit Zopfmuster</LANG>
    <LANG ID="it-IT">Parigine nere a trecce</LANG>
    <LANG ID="es-ES">Medias tres cuartos de punto de trenza negras</LANG>
    <LANG ID="ja-JP">ブラックケーブルニット・ロングソックス</LANG>
    <LANG ID="ko-KR">블랙 니트 무릎 양말 (여성)</LANG>
    <LANG ID="en-SG">Black Cable Knit Knee Socks (Women)</LANG>
    <LANG ID="zh-HK">黑色針織長筒襪（女用）</LANG>
    <LANG ID="zh-TW">黑色針織長筒襪（女用）</LANG>
    <LANG ID="en-US">Black Cable Knit Knee Socks</LANG>
  </PHRASE>
  <PHRASE>
    <LANG ID="REF">kDesc</LANG>
    <LANG ID="en-GB">Who needs shoes with socks as cute as this?! [#Legal]</LANG>
    <LANG ID="fr-FR">Qui a besoin de chaussures avec des mi-bas comme ceux-là ? [#Legal]</LANG>
    <LANG ID="de-DE">Wer braucht bei so niedlichen Strümpfen noch Schuhe?! [#Legal]</LANG>
    <LANG ID="it-IT">Chi ha bisogno delle scarpe con delle calze così carine?! [#Legal]</LANG>
    <LANG ID="es-ES">¿Quién necesita zapatos con medias tan bonitas como éstas?  [#Legal]</LANG>
    <LANG ID="ja-JP">靴もいらないほどのキュートさ！ [#Legal]</LANG>
    <LANG ID="ko-KR">이렇게 귀여운 양말이라면 신발은 필요 없을 겁니다.[#Legal]</LANG>
    <LANG ID="en-SG">Who needs shoes with socks as cute as this?! [#Legal]</LANG>
    <LANG ID="zh-HK">有這麼可愛的襪子，還需要穿鞋嗎？ [#Legal]</LANG>
    <LANG ID="zh-TW">有這麼可愛的襪子，還需要穿鞋嗎？ [#Legal]</LANG>
    <LANG ID="en-US">Who needs shoes with socks as cute as this?! [#Legal]</LANG>
  </PHRASE>
</LOCALISATION>