<?xml version="1.0" encoding="utf-8"?>
<LOCALISATION xmlns:xsi="http://www.w3.org/2001/XMLSchema-instance" xmlns:xs="http://www.w3.org/2001/XMLSchema" default_language="en-GB" xmlns="http://home.scedev.net/schema/object">
  <PHRASE>
    <LANG ID="REF">kName</LANG>
    <LANG ID="en-GB">Ungawa Collection</LANG>
    <LANG ID="fr-FR">Collection Ungawa</LANG>
    <LANG ID="de-DE">Ungawa Kollektion</LANG>
    <LANG ID="it-IT">Collezione Ungawa</LANG>
    <LANG ID="es-ES">Colección Ungawa</LANG>
    <LANG ID="ja-JP">ウンガワコレクション</LANG>
    <LANG ID="ko-KR">Ungawa 세트</LANG>
    <LANG ID="en-SG">Ungawa Collection</LANG>
    <LANG ID="zh-HK">Ungawa祖靈全套組合</LANG>
    <LANG ID="zh-TW">Ungawa祖靈全套組合</LANG>
    <LANG ID="en-US">Ungawa Collection</LANG>
  </PHRASE>
  <PHRASE>
    <LANG ID="REF">kDesc</LANG>
    <LANG ID="en-GB">All you need to join in with the legend that is Ungawa. This set includes:\n
*Ungawa Monument\n
*Ungawa Mask (Female)\n
*Ungawa Mask (Male)\n
※Upon purchase, all items will be added to their corresponding categories.[#Legal]</LANG>
    <LANG ID="fr-FR">Tout ce dont vous avez besoin pour rejoindre la légende d'Ungawa. Ce lot comprend :\n
*Monument Ungawa\n
*Masque Ungawa (Femme)\n
*Masque Ungawa (Homme)\n
※Lors de l'achat, tous les objets seront ajoutés
à leur catégorie correspondante.[#Legal]</LANG>
    <LANG ID="de-DE">Alles, was du brauchst, um Teil der Ungawa-Legende zu werden. Dieser Satz enthält:\n
*Ungawa Monument\n
*Ungawa Maske (Frau)\n
*Ungawa Maske (Mann)\n
※Beim Kauf werden alle Bekleidungsstücke ihrer entsprechenden Kategorie zugeordnet.[#Legal]</LANG>
    <LANG ID="it-IT">Tutto l'occorrente per far parte della tribù Ungawa. Il set include:\n
*Monumento Ungawa\n
*Maschera Ungawa (donna)\n
*Maschera Ungawa (uomo)\n
※Effettuato l'ordine, ogni accessorio sarà aggiunto alla categoria corrispondente.[#Legal]</LANG>
    <LANG ID="es-ES">Todo lo que necesitas para tomar parte en la leyenda de Ungawa. Este lote incluye:\n
*Monumento ungawa\n
*Máscara ungawa (mujer)\n
*Máscara ungawa (Hombre)\n
※En el momento de la compra, todos los artículos se añadirán a sus correspondientes categorías.[#Legal]</LANG>
    <LANG ID="ja-JP">マスクを着けて、ウンガワモニュメントに近づけば、伝説の精霊・ウンガワにあなたも出会えます。\n\n本セットには、以下のアイテムが含まれています。\n\n
-ウンガワモニュメント（家電・器具）\n
-ウンガワマスク (女性用・フェイスアクセサリ)\n
-ウンガワマスク (男性用・フェイスアクセサリ)\n\n
※購入すると、「アバターのカスタマイズ」、「プライベートラウンジのカスタマイズ」内の該当カテゴリに各アイテムが追加されます。\n\nまたこのアイテムには、アニメーションや機能が追加されているアドバンスド家具が含まれています。\nこの種類のアイテムは配置できる数に制限があります。[#Legal]</LANG>
    <LANG ID="ko-KR">Ungawa라는 이름의 전설과 하나가 될 수 있는 기회입니다. 이 세트는 다음을 포함합니다:\n
*Ungawa 기념비\n
*Ungawa 마스크 (남성)\n
*Ungawa 마스크 (여성)\n
※구입한 아이템들은 해당 카테고리에 자동으로 추가됩니다.[#Legal]</LANG>
    <LANG ID="en-SG">All you need to join in with the legend that is Ungawa. This set includes:\n
*Ungawa Monument\n
*Ungawa Mask (Women)\n
*Ungawa Mask (Men)\n
※Upon purchase, all items will be added to their corresponding categories.[#Legal]</LANG>
    <LANG ID="zh-HK">這款全套組合提供您在體驗Ungawa傳說時所有需要的物品。本組合包含以下物品：\n
●Ungawa祖靈紀念碑\n
●Ungawa祖靈面具(男用)\n
●Ungawa祖靈面具(女用)\n
※已購入的物件會追加到各項所屬類別裡。[#Legal]</LANG>
    <LANG ID="zh-TW">這款全套組合提供您在體驗Ungawa傳說時所有需要的物品。本組合包含以下物品：\n
●Ungawa祖靈紀念碑\n
●Ungawa祖靈面具(男用)\n
●Ungawa祖靈面具(女用)\n
※已購入的物件會追加到各項所屬類別裡。[#Legal]</LANG>
    <LANG ID="en-US">All you need to join in with the legend that is Ungawa. This set includes:\n
*Ungawa Monument\n
*Ungawa Mask (Female)\n
*Ungawa Mask (Male)\n
※Upon purchase, all items will be added to their corresponding categories.[#Legal]</LANG>
  </PHRASE>
</LOCALISATION>