<object uuid="83A9771F-54A0454C-AA734CF1-4CF3B8E6"><CATEGORY_ID>EP4065-NPER00003_00 HT4005-NPHR00020_00 UT5002-NPUR00030_00 </CATEGORY_ID><ENTITLEMENT_ID>EP4065-NPER00003_00-001672 HT4005-NPHR00020_00-000673 UT5002-NPUR00030_00-003559 </ENTITLEMENT_ID><FURNITURE>ORNAMENT </FURNITURE><HOST_HEAT>1 </HOST_HEAT><MAIN_HEAT>1 </MAIN_HEAT><NET_HEAT>1 </NET_HEAT><PPU_HEAT>1 </PPU_HEAT><PRODUCT_ID>EP4065-NPER00003_00-MYBEDROOMB001672 HT4005-NPHR00020_00-0006730000000000 UT5002-NPUR00030_00-0035590000000000 </PRODUCT_ID><VRAM_HEAT>1 </VRAM_HEAT></object>
