<?xml version="1.0" encoding="utf-8"?>
<LOCALISATION xmlns:xsi="http://www.w3.org/2001/XMLSchema-instance" xmlns:xs="http://www.w3.org/2001/XMLSchema" default_language="en-US" xmlns="http://home.scedev.net/schema/object">
  <PHRASE>
    <LANG ID="REF">kName</LANG>
    <LANG ID="en-GB">"Patron" Black and Grey Plaid Jeans</LANG>
    <LANG ID="fr-FR">Jean Écossais Gris et Noir 'Bienfaiteur'</LANG>
    <LANG ID="de-DE">Schwarz-graue Plaid-Jeans "Patron"</LANG>
    <LANG ID="it-IT">Jeans di panno taglio sartoriale nero e grigio</LANG>
    <LANG ID="es-ES">Vaqueros de cuadros negros y grises "Patrón"</LANG>
    <LANG ID="ja-JP">「PATRON」プレイドジーンズ（ブラック・グレイ）</LANG>
    <LANG ID="ko-KR">"패트론" 플레이드 청바지 (남성)</LANG>
    <LANG ID="en-SG">"Patron" Black and Grey Plaid Jeans (Men)</LANG>
    <LANG ID="zh-HK">「高尚」黑灰格子牛仔褲（男用）</LANG>
    <LANG ID="zh-TW">「高尚」黑灰格子牛仔褲（男用）</LANG>
    <LANG ID="en-US">"Patron" Black and Grey Plaid Jeans</LANG>
  </PHRASE>
  <PHRASE>
    <LANG ID="REF">kDesc</LANG>
    <LANG ID="en-GB">Dressing up or dressing down? Either way, these are the jeans. [#Legal]</LANG>
    <LANG ID="fr-FR">Vous devez vous habiller classe ? Décontracté ? Dans tous les cas, voici le jean qu'il vous faut. [#Legal]</LANG>
    <LANG ID="de-DE">Schick oder locker? Diese Jeans ist in jedem Fall ein Volltreffer. [#Legal]</LANG>
    <LANG ID="it-IT">Elegante o sportivo? Qualunque sia lo stile, questi sono i jeans. [#Legal]</LANG>
    <LANG ID="es-ES">¿Estilo formal o informal? ¡Qué más da! Estos son tus vaqueros.  [#Legal]</LANG>
    <LANG ID="ja-JP">どんな場面にも持って来いです！[#Legal]</LANG>
    <LANG ID="ko-KR">정장인가요, 캐주얼인가요? 둘 모두 잘 어울리는 청바지입니다. [#Legal]</LANG>
    <LANG ID="en-SG">Dressing up or dressing down? Either way, these are the jeans. [#Legal]</LANG>
    <LANG ID="zh-HK">你想盛裝打扮還是刻意低調？不管怎麼樣，穿這條準沒錯。 [#Legal]</LANG>
    <LANG ID="zh-TW">你想盛裝打扮還是刻意低調？不管怎麼樣，穿這條準沒錯。 [#Legal]</LANG>
    <LANG ID="en-US">Dressing up or dressing down? Either way, these are the jeans. [#Legal]</LANG>
  </PHRASE>
</LOCALISATION>