<?xml version="1.0" encoding="utf-8"?>
<LOCALISATION xmlns:xsi="http://www.w3.org/2001/XMLSchema-instance" xmlns:xs="http://www.w3.org/2001/XMLSchema" default_language="en-GB" xmlns="http://home.scedev.net/schema/object">
  <PHRASE>
    <LANG ID="REF">Shiny Blue Sneakers</LANG>
    <LANG ID="en-GB">*Not Localised* Shiny Blue Sneakers</LANG>
    <LANG ID="fr-FR">*Not Localised* Shiny Blue Sneakers</LANG>
    <LANG ID="de-DE">*Not Localised* Shiny Blue Sneakers</LANG>
    <LANG ID="it-IT">*Not Localised* Shiny Blue Sneakers</LANG>
    <LANG ID="es-ES">*Not Localised* Shiny Blue Sneakers</LANG>
    <LANG ID="ja-JP">*Not Localised* Shiny Blue Sneakers</LANG>
    <LANG ID="ko-KR">*Not Localised* Shiny Blue Sneakers</LANG>
    <LANG ID="en-SG">*Not Localised* Shiny Blue Sneakers</LANG>
    <LANG ID="zh-HK">*Not Localised* Shiny Blue Sneakers</LANG>
    <LANG ID="zh-TW">*Not Localised* Shiny Blue Sneakers</LANG>
    <LANG ID="en-US">*Not Localised* Shiny Blue Sneakers</LANG>
  </PHRASE>
  <PHRASE>
    <LANG ID="REF">A little spray paints really livens up a pair of old shoes.</LANG>
    <LANG ID="en-GB">*Not Localised* A little spray paints really livens up a pair of old shoes.</LANG>
    <LANG ID="fr-FR">*Not Localised* A little spray paints really livens up a pair of old shoes.</LANG>
    <LANG ID="de-DE">*Not Localised* A little spray paints really livens up a pair of old shoes.</LANG>
    <LANG ID="it-IT">*Not Localised* A little spray paints really livens up a pair of old shoes.</LANG>
    <LANG ID="es-ES">*Not Localised* A little spray paints really livens up a pair of old shoes.</LANG>
    <LANG ID="ja-JP">*Not Localised* A little spray paints really livens up a pair of old shoes.</LANG>
    <LANG ID="ko-KR">*Not Localised* A little spray paints really livens up a pair of old shoes.</LANG>
    <LANG ID="en-SG">*Not Localised* A little spray paints really livens up a pair of old shoes.</LANG>
    <LANG ID="zh-HK">*Not Localised* A little spray paints really livens up a pair of old shoes.</LANG>
    <LANG ID="zh-TW">*Not Localised* A little spray paints really livens up a pair of old shoes.</LANG>
    <LANG ID="en-US">*Not Localised* A little spray paints really livens up a pair of old shoes.</LANG>
  </PHRASE>
</LOCALISATION>